{"files":[{"name":"ﾊﾞｯｸの音 69~.mp3","ref":[0,0,755670]},{"name":"ﾊﾞｯｸの音 3~.mp3","ref":[0,755670,1277283]},{"name":"ﾊﾞｯｸの音 33~.mp3","ref":[1,0,497371]},{"name":"square 92-1.mp3","ref":[1,497371,557139]},{"name":"ﾋﾟｱﾉ 4-5-2.mp3","ref":[1,557139,616489]},{"name":"ﾋﾟｱﾉ 4-4.mp3","ref":[1,616489,675839]},{"name":"ﾋﾟｱﾉ 4-1.mp3","ref":[1,675839,735189]},{"name":"ﾋﾟｱﾉ 4-10-1.mp3","ref":[1,735189,794539]},{"name":"ﾋﾟｱﾉ 4-6-1.mp3","ref":[1,794539,853889]},{"name":"ﾋﾟｱﾉ 4-6-2.mp3","ref":[1,853889,913239]},{"name":"ﾋﾟｱﾉ 4-7.mp3","ref":[1,913239,972589]},{"name":"ﾋﾟｱﾉ 4-8-1.mp3","ref":[1,972589,1031939]},{"name":"ﾋﾟｱﾉ 4-8-2.mp3","ref":[1,1031939,1091289]},{"name":"ﾋﾟｱﾉ 4-9.mp3","ref":[1,1091289,1150639]},{"name":"ﾋﾟｱﾉ 4-3-2.mp3","ref":[1,1150639,1209989]},{"name":"ﾋﾟｱﾉ 4-3-1.mp3","ref":[1,1209989,1269339]},{"name":"ﾋﾟｱﾉ 4-5-1.mp3","ref":[1,1269339,1328689]},{"name":"ﾋﾟｱﾉ 4-11.mp3","ref":[1,1328689,1388039]},{"name":"ﾋﾟｱﾉ 4-10-2.mp3","ref":[1,1388039,1447389]},{"name":"ﾋﾟｱﾉ 4-2.mp3","ref":[2,0,59350]},{"name":"25% 99-1-1.mp3","ref":[2,59350,118282]},{"name":"square 9-1.mp3","ref":[2,118282,172198]},{"name":"triangle 99-1-3.mp3","ref":[2,172198,220681]},{"name":"ｼﾝｾﾄﾞﾗﾑ symbal+ｼｬﾗｰﾝ.mp3","ref":[2,220681,269164]},{"name":"triangle 99-1-2.mp3","ref":[2,269164,317647]},{"name":"triangle 99-1-1.mp3","ref":[2,317647,366130]},{"name":"triangle 100-1.mp3","ref":[2,366130,414613]},{"name":"ﾄﾞﾗﾑ 8 snare roll.mp3","ref":[2,414613,462678]},{"name":"ﾋﾟｱﾉ 47-1-2.mp3","ref":[2,462678,509907]},{"name":"ﾋﾟｱﾉ 47-1-1.mp3","ref":[2,509907,557136]},{"name":"ﾋﾟｱﾉ 47-2-1.mp3","ref":[2,557136,604365]},{"name":"ﾋﾟｱﾉ 47-2-2.mp3","ref":[2,604365,651594]},{"name":"口笛　56-1.mp3","ref":[2,651594,697569]},{"name":"triangle 39-1.mp3","ref":[2,697569,741872]},{"name":"ﾄﾞﾗﾑ C2E symbal.mp3","ref":[2,741872,781578]},{"name":"25% 100-1.mp3","ref":[2,781578,821284]},{"name":"ﾄﾞﾗﾑ C2A symbal.mp3","ref":[2,821284,860990]},{"name":"ﾋﾟｱﾉ 44-1.mp3","ref":[2,860990,897770]},{"name":"25% 98-1-1.mp3","ref":[2,897770,934550]},{"name":"ﾋﾟｱﾉ 41-1.mp3","ref":[2,934550,971330]},{"name":"ﾋﾟｱﾉ 41-2.mp3","ref":[2,971330,1008110]},{"name":"ﾋﾟｱﾉ 41-3.mp3","ref":[2,1008110,1044890]},{"name":"ﾋﾟｱﾉ 44-3.mp3","ref":[2,1044890,1081670]},{"name":"25% 98-1-2.mp3","ref":[2,1081670,1118450]},{"name":"ﾋﾟｱﾉ 43-3.mp3","ref":[2,1118450,1155230]},{"name":"ﾋﾟｱﾉ 43-2.mp3","ref":[2,1155230,1192010]},{"name":"ﾋﾟｱﾉ 42-1.mp3","ref":[2,1192010,1228790]},{"name":"ﾋﾟｱﾉ 43-1.mp3","ref":[2,1228790,1265570]},{"name":"ﾋﾟｱﾉ 44-2.mp3","ref":[2,1265570,1302350]},{"name":"ﾋﾟｱﾉ 42-2.mp3","ref":[2,1302350,1339130]},{"name":"ﾋﾟｱﾉ 42-3.mp3","ref":[2,1339130,1375910]},{"name":"ﾋﾟｱﾉ 42-4-1.mp3","ref":[2,1375910,1412690]},{"name":"ﾋﾟｱﾉ 42-4-2.mp3","ref":[2,1412690,1449470]},{"name":"ﾄﾗﾝﾍﾟｯﾄ　52-2.mp3","ref":[3,0,35526]},{"name":"ﾄﾗﾝﾍﾟｯﾄ　49-1.mp3","ref":[3,35526,71052]},{"name":"ﾄﾗﾝﾍﾟｯﾄ　50-1-1.mp3","ref":[3,71052,106578]},{"name":"ﾋﾟｱﾉ 46-1-2.mp3","ref":[3,106578,142104]},{"name":"ﾋﾟｱﾉ 46-1-1.mp3","ref":[3,142104,177630]},{"name":"ﾋﾟｱﾉ 45-1-2.mp3","ref":[3,177630,213156]},{"name":"ｶﾘｵﾍﾟ　47-2.mp3","ref":[3,213156,248682]},{"name":"ﾋﾟｱﾉ 45-1-1.mp3","ref":[3,248682,284208]},{"name":"ﾄﾗﾝﾍﾟｯﾄ　52-1-2.mp3","ref":[3,284208,319734]},{"name":"ﾄﾗﾝﾍﾟｯﾄ　50-1-2.mp3","ref":[3,319734,355260]},{"name":"25% 55-1-2.mp3","ref":[3,355260,389950]},{"name":"25% 54-1-2.mp3","ref":[3,389950,424640]},{"name":"25% 53-1-1.mp3","ref":[3,424640,459330]},{"name":"25% 53-1-2.mp3","ref":[3,459330,494020]},{"name":"triangle 90-1.mp3","ref":[3,494020,528710]},{"name":"25% 54-1-1.mp3","ref":[3,528710,563400]},{"name":"25% 54-2.mp3","ref":[3,563400,598090]},{"name":"25% 55-1-1.mp3","ref":[3,598090,632780]},{"name":"triangle 88-1.mp3","ref":[3,632780,667470]},{"name":"25% 56-1-1.mp3","ref":[3,667470,701742]},{"name":"25% 56-1-2.mp3","ref":[3,701742,736014]},{"name":"ﾋﾟｱﾉ 41-5.mp3","ref":[3,736014,768614]},{"name":"ﾋﾟｱﾉ 41-4.mp3","ref":[3,768614,801214]},{"name":"ﾋﾟｱﾉ 41-6.mp3","ref":[3,801214,833814]},{"name":"ﾋﾟｱﾉ 41-7-1.mp3","ref":[3,833814,866414]},{"name":"ﾋﾟｱﾉ 41-8.mp3","ref":[3,866414,899014]},{"name":"ﾋﾟｱﾉ 41-7-2.mp3","ref":[3,899014,931614]},{"name":"12.5% 13-1.mp3","ref":[3,931614,963796]},{"name":"25% 68-3.mp3","ref":[3,963796,995560]},{"name":"25% 68-1-2.mp3","ref":[3,995560,1027324]},{"name":"25% 68-4.mp3","ref":[3,1027324,1059088]},{"name":"25% 68-2.mp3","ref":[3,1059088,1090852]},{"name":"25% 68-1-3.mp3","ref":[3,1090852,1122616]},{"name":"25% 68-1-1.mp3","ref":[3,1122616,1154380]},{"name":"square 8-1.mp3","ref":[3,1154380,1185309]},{"name":"25% 66-1-1.mp3","ref":[3,1185309,1215820]},{"name":"25% 99-1-2.mp3","ref":[3,1215820,1246331]},{"name":"25% 67-1-2.mp3","ref":[3,1246331,1276424]},{"name":"ﾄﾗﾝﾍﾟｯﾄ　50-3.mp3","ref":[3,1276424,1306099]},{"name":"ﾄﾗﾝﾍﾟｯﾄ　50-4.mp3","ref":[3,1306099,1335774]},{"name":"25% 66-1-2.mp3","ref":[3,1335774,1365449]},{"name":"12.5% 15-2.mp3","ref":[3,1365449,1395124]},{"name":"ﾄﾗﾝﾍﾟｯﾄ　51-1-2.mp3","ref":[3,1395124,1424799]},{"name":"ﾄﾗﾝﾍﾟｯﾄ　51-2-1.mp3","ref":[3,1424799,1454474]},{"name":"ﾄﾗﾝﾍﾟｯﾄ　51-2-2.mp3","ref":[4,0,29675]},{"name":"ﾄﾗﾝﾍﾟｯﾄ　50-2.mp3","ref":[4,29675,59350]},{"name":"ﾄﾗﾝﾍﾟｯﾄ　51-1-1.mp3","ref":[4,59350,89025]},{"name":"ﾄﾗﾝﾍﾟｯﾄ　52-1-1.mp3","ref":[4,89025,118700]},{"name":"square 8-2.mp3","ref":[4,118700,147957]},{"name":"square 7-3.mp3","ref":[4,147957,177214]},{"name":"square 40-1-2.mp3","ref":[4,177214,206471]},{"name":"square 40-1-1.mp3","ref":[4,206471,235728]},{"name":"ﾋﾟｱﾉ 41-10.mp3","ref":[4,235728,264149]},{"name":"ﾋﾟｱﾉ 44-6.mp3","ref":[4,264149,292570]},{"name":"ﾋﾟｱﾉ 44-5.mp3","ref":[4,292570,320991]},{"name":"ﾋﾟｱﾉ 44-4.mp3","ref":[4,320991,349412]},{"name":"ﾋﾟｱﾉ 41-9.mp3","ref":[4,349412,377833]},{"name":"triangle 39-code.mp3","ref":[4,377833,404582]},{"name":"ﾋﾟｱﾉ 43-6.mp3","ref":[4,404582,431331]},{"name":"triangle 38-code.mp3","ref":[4,431331,458080]},{"name":"triangle 37-code.mp3","ref":[4,458080,484829]},{"name":"triangle 36-code.mp3","ref":[4,484829,511578]},{"name":"triangle 35-code.mp3","ref":[4,511578,538327]},{"name":"25% 66-1-3.mp3","ref":[4,538327,565076]},{"name":"triangle 40-code.mp3","ref":[4,565076,591825]},{"name":"triangle 34-code.mp3","ref":[4,591825,618574]},{"name":"triangle 33-code.mp3","ref":[4,618574,645323]},{"name":"triangle 32-code.mp3","ref":[4,645323,672072]},{"name":"triangle 31-code.mp3","ref":[4,672072,698821]},{"name":"triangle 30-code.mp3","ref":[4,698821,725570]},{"name":"triangle 29-code.mp3","ref":[4,725570,752319]},{"name":"ﾋﾟｱﾉ 43-10.mp3","ref":[4,752319,779068]},{"name":"ﾋﾟｱﾉ 43-5-1.mp3","ref":[4,779068,805817]},{"name":"triangle 28-code.mp3","ref":[4,805817,832566]},{"name":"triangle 27-code.mp3","ref":[4,832566,859315]},{"name":"ﾋﾟｱﾉ 43-5-2.mp3","ref":[4,859315,886064]},{"name":"ﾋﾟｱﾉ 43-9.mp3","ref":[4,886064,912813]},{"name":"triangle 26-code.mp3","ref":[4,912813,939562]},{"name":"ﾋﾟｱﾉ 43-8.mp3","ref":[4,939562,966311]},{"name":"ﾋﾟｱﾉ 43-7.mp3","ref":[4,966311,993060]},{"name":"triangle 25-code.mp3","ref":[4,993060,1019809]},{"name":"ﾄﾞﾗﾑ 6 snare roll.mp3","ref":[4,1019809,1045304]},{"name":"25% 67-1-1.mp3","ref":[4,1045304,1070381]},{"name":"ﾄﾗﾝﾍﾟｯﾄ　6-3-1.mp3","ref":[4,1070381,1095458]},{"name":"ﾄﾗﾝﾍﾟｯﾄ　6-3-2.mp3","ref":[4,1095458,1120535]},{"name":"triangle 98-1-1.mp3","ref":[4,1120535,1145194]},{"name":"triangle 98-1-2.mp3","ref":[4,1145194,1169853]},{"name":"12.5% 73-1.mp3","ref":[4,1169853,1194512]},{"name":"ﾄﾗﾝﾍﾟｯﾄ　50_-2.mp3","ref":[4,1194512,1218335]},{"name":"ﾄﾗﾝﾍﾟｯﾄ　51_-1.mp3","ref":[4,1218335,1242158]},{"name":"ﾋﾟｱﾉ 48-2-2.mp3","ref":[4,1242158,1265981]},{"name":"ﾄﾗﾝﾍﾟｯﾄ　51_-2.mp3","ref":[4,1265981,1289804]},{"name":"ﾄﾗﾝﾍﾟｯﾄ　52_-3.mp3","ref":[4,1289804,1313627]},{"name":"ﾄﾗﾝﾍﾟｯﾄ　51_-3.mp3","ref":[4,1313627,1337450]},{"name":"ﾄﾗﾝﾍﾟｯﾄ　51_-4.mp3","ref":[4,1337450,1361273]},{"name":"25% 69-1-1.mp3","ref":[4,1361273,1385096]},{"name":"25% 69-1-2.mp3","ref":[4,1385096,1408919]},{"name":"25% 69-1-3.mp3","ref":[4,1408919,1432742]},{"name":"ﾋﾟｱﾉ 46-2.mp3","ref":[4,1432742,1456565]},{"name":"ﾋﾟｱﾉ 48-1-1.mp3","ref":[5,0,23823]},{"name":"ﾋﾟｱﾉ 48-2-1.mp3","ref":[5,23823,47646]},{"name":"square 75-2.mp3","ref":[5,47646,71469]},{"name":"ﾄﾗﾝﾍﾟｯﾄ　52_-1.mp3","ref":[5,71469,95292]},{"name":"ﾋﾟｱﾉ 48-1-2.mp3","ref":[5,95292,119115]},{"name":"ﾋﾟｱﾉ 3-6.mp3","ref":[5,119115,142520]},{"name":"口笛　55-3.mp3","ref":[5,142520,165925]},{"name":"ﾋﾟｱﾉ 3-5.mp3","ref":[5,165925,189330]},{"name":"square 89-4.mp3","ref":[5,189330,212735]},{"name":"square 89-3.mp3","ref":[5,212735,236140]},{"name":"square 89-2.mp3","ref":[5,236140,259545]},{"name":"square 89-1.mp3","ref":[5,259545,282950]},{"name":"square 88-4.mp3","ref":[5,282950,306355]},{"name":"square 88-3.mp3","ref":[5,306355,329760]},{"name":"square 88-2.mp3","ref":[5,329760,353165]},{"name":"square 88-1.mp3","ref":[5,353165,376570]},{"name":"square 87-5.mp3","ref":[5,376570,399975]},{"name":"square 87-4.mp3","ref":[5,399975,423380]},{"name":"square 87-3.mp3","ref":[5,423380,446785]},{"name":"square 87-2.mp3","ref":[5,446785,470190]},{"name":"square 87-1.mp3","ref":[5,470190,493595]},{"name":"square 86-6.mp3","ref":[5,493595,517000]},{"name":"ﾋﾟｱﾉ 3-4.mp3","ref":[5,517000,540405]},{"name":"square 86-4.mp3","ref":[5,540405,563810]},{"name":"square 86-3.mp3","ref":[5,563810,587215]},{"name":"square 86-2.mp3","ref":[5,587215,610620]},{"name":"square 86-1.mp3","ref":[5,610620,634025]},{"name":"square 85-4.mp3","ref":[5,634025,657430]},{"name":"square 85-3.mp3","ref":[5,657430,680835]},{"name":"square 85-2.mp3","ref":[5,680835,704240]},{"name":"square 85-1.mp3","ref":[5,704240,727645]},{"name":"square 84-7.mp3","ref":[5,727645,751050]},{"name":"square 84-6.mp3","ref":[5,751050,774455]},{"name":"square 84-5.mp3","ref":[5,774455,797860]},{"name":"square 84-4.mp3","ref":[5,797860,821265]},{"name":"口笛　55-1.mp3","ref":[5,821265,844670]},{"name":"ﾋﾟｱﾉ 3-3.mp3","ref":[5,844670,868075]},{"name":"ﾋﾟｱﾉ 3-2.mp3","ref":[5,868075,891480]},{"name":"ﾋﾟｱﾉ 3-12.mp3","ref":[5,891480,914885]},{"name":"ﾋﾟｱﾉ 3-11.mp3","ref":[5,914885,938290]},{"name":"25% 67-2.mp3","ref":[5,938290,961695]},{"name":"ﾋﾟｱﾉ 3-10.mp3","ref":[5,961695,985100]},{"name":"口笛　52-1.mp3","ref":[5,985100,1008505]},{"name":"口笛　53-1.mp3","ref":[5,1008505,1031910]},{"name":"口笛　53-2.mp3","ref":[5,1031910,1055315]},{"name":"口笛　53-3.mp3","ref":[5,1055315,1078720]},{"name":"口笛　54-1.mp3","ref":[5,1078720,1102125]},{"name":"ﾋﾟｱﾉ 3-1.mp3","ref":[5,1102125,1125530]},{"name":"口笛　54-4.mp3","ref":[5,1125530,1148935]},{"name":"ﾋﾟｱﾉ 3-9.mp3","ref":[5,1148935,1172340]},{"name":"square 84-3.mp3","ref":[5,1172340,1195745]},{"name":"square 84-2.mp3","ref":[5,1195745,1219150]},{"name":"square 84-1.mp3","ref":[5,1219150,1242555]},{"name":"square 83-4.mp3","ref":[5,1242555,1265960]},{"name":"square 83-3.mp3","ref":[5,1265960,1289365]},{"name":"square 83-2.mp3","ref":[5,1289365,1312770]},{"name":"square 83-1.mp3","ref":[5,1312770,1336175]},{"name":"口笛　54-2.mp3","ref":[5,1336175,1359580]},{"name":"口笛　55-2.mp3","ref":[5,1359580,1382985]},{"name":"口笛　54-3.mp3","ref":[5,1382985,1406390]},{"name":"12.5% 70-3.mp3","ref":[5,1406390,1429795]},{"name":"口笛　55-5.mp3","ref":[5,1429795,1453200]},{"name":"square 74-4.mp3","ref":[6,0,23405]},{"name":"口笛　55-4.mp3","ref":[6,23405,46810]},{"name":"square 75-4.mp3","ref":[6,46810,70215]},{"name":"ﾋﾟｱﾉ 3-8.mp3","ref":[6,70215,93620]},{"name":"ﾋﾟｱﾉ 3-7.mp3","ref":[6,93620,117025]},{"name":"square 76-1.mp3","ref":[6,117025,140430]},{"name":"square 79-1.mp3","ref":[6,140430,163835]},{"name":"square 86-5.mp3","ref":[6,163835,187240]},{"name":"square 78-4.mp3","ref":[6,187240,210227]},{"name":"square 77-3.mp3","ref":[6,210227,233214]},{"name":"square 76-3.mp3","ref":[6,233214,256201]},{"name":"square 79-5.mp3","ref":[6,256201,279188]},{"name":"square 75-3.mp3","ref":[6,279188,302175]},{"name":"square 81-6.mp3","ref":[6,302175,325162]},{"name":"square 91-1.mp3","ref":[6,325162,348149]},{"name":"square 77-1.mp3","ref":[6,348149,370718]},{"name":"square 80-1.mp3","ref":[6,370718,393287]},{"name":"square 76-4.mp3","ref":[6,393287,415856]},{"name":"square 81-1.mp3","ref":[6,415856,438425]},{"name":"square 74-6.mp3","ref":[6,438425,460994]},{"name":"square 78-6.mp3","ref":[6,460994,483563]},{"name":"square 79-2.mp3","ref":[6,483563,506132]},{"name":"square 90-3.mp3","ref":[6,506132,528701]},{"name":"square 57-7.mp3","ref":[6,528701,551270]},{"name":"square 57-6.mp3","ref":[6,551270,573839]},{"name":"square 57-5.mp3","ref":[6,573839,596408]},{"name":"square 57-4.mp3","ref":[6,596408,618977]},{"name":"square 57-3.mp3","ref":[6,618977,641546]},{"name":"square 57-2.mp3","ref":[6,641546,664115]},{"name":"square 57-1.mp3","ref":[6,664115,686684]},{"name":"ｶﾘｵﾍﾟ　43-1.mp3","ref":[6,686684,709253]},{"name":"square 90-5.mp3","ref":[6,709253,731822]},{"name":"square 76-2.mp3","ref":[6,731822,754391]},{"name":"square 81-4.mp3","ref":[6,754391,776960]},{"name":"square 91-2.mp3","ref":[6,776960,799111]},{"name":"square 74-7.mp3","ref":[6,799111,821262]},{"name":"square 74-2.mp3","ref":[6,821262,843413]},{"name":"square 82-7.mp3","ref":[6,843413,865564]},{"name":"square 80-5.mp3","ref":[6,865564,887715]},{"name":"square 74-1.mp3","ref":[6,887715,909866]},{"name":"square 80-3.mp3","ref":[6,909866,932017]},{"name":"square 82-2.mp3","ref":[6,932017,954168]},{"name":"square 82-1.mp3","ref":[6,954168,976319]},{"name":"square 81-3.mp3","ref":[6,976319,998052]},{"name":"square 90-4.mp3","ref":[6,998052,1019785]},{"name":"triangle 27_-1.mp3","ref":[6,1019785,1041518]},{"name":"triangle 27_-2.mp3","ref":[6,1041518,1063251]},{"name":"triangle 27-2.mp3","ref":[6,1063251,1084984]},{"name":"square 82-8.mp3","ref":[6,1084984,1106717]},{"name":"triangle 37-3.mp3","ref":[6,1106717,1128450]},{"name":"triangle 38-1.mp3","ref":[6,1128450,1150183]},{"name":"square 74-5.mp3","ref":[6,1150183,1171916]},{"name":"square 80-4.mp3","ref":[6,1171916,1193649]},{"name":"triangle 38-2.mp3","ref":[6,1193649,1215382]},{"name":"triangle 38-3.mp3","ref":[6,1215382,1237115]},{"name":"triangle 38-4.mp3","ref":[6,1237115,1258848]},{"name":"square 79-3.mp3","ref":[6,1258848,1280581]},{"name":"square 78-5.mp3","ref":[6,1280581,1302314]},{"name":"square 78-1.mp3","ref":[6,1302314,1324047]},{"name":"square 77-4.mp3","ref":[6,1324047,1345780]},{"name":"25% 65-5-1.mp3","ref":[6,1345780,1367095]},{"name":"square 81-2.mp3","ref":[6,1367095,1388410]},{"name":"square 90-1.mp3","ref":[6,1388410,1409725]},{"name":"square 76-5.mp3","ref":[6,1409725,1431040]},{"name":"12.5% 72-1.mp3","ref":[6,1431040,1452355]},{"name":"square 79-4.mp3","ref":[6,1452355,1473670]},{"name":"12.5% 72-10.mp3","ref":[7,0,21315]},{"name":"25% 64-1.mp3","ref":[7,21315,42630]},{"name":"25% 64-2.mp3","ref":[7,42630,63945]},{"name":"square 80-2.mp3","ref":[7,63945,85260]},{"name":"square 75-1.mp3","ref":[7,85260,106575]},{"name":"25% 64-3-1.mp3","ref":[7,106575,127890]},{"name":"25% 64-3-2.mp3","ref":[7,127890,149205]},{"name":"25% 64-4.mp3","ref":[7,149205,170520]},{"name":"25% 64-5-1.mp3","ref":[7,170520,191835]},{"name":"25% 64-5-2.mp3","ref":[7,191835,213150]},{"name":"25% 65-1-1.mp3","ref":[7,213150,234465]},{"name":"25% 65-1-2.mp3","ref":[7,234465,255780]},{"name":"25% 65-1-3.mp3","ref":[7,255780,277095]},{"name":"25% 65-6.mp3","ref":[7,277095,298410]},{"name":"25% 65-5-2.mp3","ref":[7,298410,319725]},{"name":"25% 65-2.mp3","ref":[7,319725,341040]},{"name":"25% 65-4.mp3","ref":[7,341040,362355]},{"name":"25% 65-3-2.mp3","ref":[7,362355,383670]},{"name":"25% 65-3-1.mp3","ref":[7,383670,404985]},{"name":"square 74-3.mp3","ref":[7,404985,425882]},{"name":"square 78-2.mp3","ref":[7,425882,446779]},{"name":"square 82-6.mp3","ref":[7,446779,467676]},{"name":"square 82-5.mp3","ref":[7,467676,488573]},{"name":"square 82-4.mp3","ref":[7,488573,509470]},{"name":"square 82-3.mp3","ref":[7,509470,530367]},{"name":"square 90-2.mp3","ref":[7,530367,551264]},{"name":"12.5% 71-1.mp3","ref":[7,551264,572161]},{"name":"ﾄﾗﾝﾍﾟｯﾄ　49_-2.mp3","ref":[7,572161,593058]},{"name":"square 77-2.mp3","ref":[7,593058,613955]},{"name":"ﾄﾗﾝﾍﾟｯﾄ　89-1-1.mp3","ref":[7,613955,634435]},{"name":"ﾄﾗﾝﾍﾟｯﾄ　89-1-2.mp3","ref":[7,634435,654915]},{"name":"ﾄﾗﾝﾍﾟｯﾄ　88-2-1.mp3","ref":[7,654915,675395]},{"name":"ﾄﾗﾝﾍﾟｯﾄ　89-2-1.mp3","ref":[7,675395,695875]},{"name":"ﾄﾗﾝﾍﾟｯﾄ　89-2-2.mp3","ref":[7,695875,716355]},{"name":"square 78-3.mp3","ref":[7,716355,736835]},{"name":"ﾄﾗﾝﾍﾟｯﾄ　88-2-2.mp3","ref":[7,736835,757315]},{"name":"ﾋﾟｱﾉ 2-7-2.mp3","ref":[7,757315,777377]},{"name":"square 2-3.mp3","ref":[7,777377,797439]},{"name":"triangle 5-2.mp3","ref":[7,797439,817501]},{"name":"ﾄﾞﾗﾑ bass first.mp3","ref":[7,817501,837563]},{"name":"ﾋﾟｱﾉ 1-8-1.mp3","ref":[7,837563,857625]},{"name":"ﾄﾗﾝﾍﾟｯﾄ　5-3-2.mp3","ref":[7,857625,877687]},{"name":"square 82-9.mp3","ref":[7,877687,897749]},{"name":"ﾄﾞﾗﾑ bass other.mp3","ref":[7,897749,917811]},{"name":"ﾋﾟｱﾉ 2-6-2.mp3","ref":[7,917811,937873]},{"name":"ﾄﾞﾗﾑ C2G symbal.mp3","ref":[7,937873,957935]},{"name":"ﾋﾟｱﾉ 2-6-1.mp3","ref":[7,957935,977997]},{"name":"ﾋﾟｱﾉ 2-5.mp3","ref":[7,977997,998059]},{"name":"ﾋﾟｱﾉ 1-3.mp3","ref":[7,998059,1018121]},{"name":"ﾄﾞﾗﾑ C2F symbal.mp3","ref":[7,1018121,1038183]},{"name":"ﾋﾟｱﾉ 2-4.mp3","ref":[7,1038183,1058245]},{"name":"ﾄﾗﾝﾍﾟｯﾄ　6-1-1.mp3","ref":[7,1058245,1078307]},{"name":"ﾄﾗﾝﾍﾟｯﾄ　6-1-2.mp3","ref":[7,1078307,1098369]},{"name":"triangle 5-4.mp3","ref":[7,1098369,1118431]},{"name":"ﾋﾟｱﾉ 2-7-1.mp3","ref":[7,1118431,1138493]},{"name":"square 1-1.mp3","ref":[7,1138493,1158555]},{"name":"triangle 5-1.mp3","ref":[7,1158555,1178617]},{"name":"square 2-5.mp3","ref":[7,1178617,1198679]},{"name":"ﾋﾟｱﾉ 2-3.mp3","ref":[7,1198679,1218741]},{"name":"triangle 5-3.mp3","ref":[7,1218741,1238803]},{"name":"ﾋﾟｱﾉ 1-7-2.mp3","ref":[7,1238803,1258865]},{"name":"ﾋﾟｱﾉ 1-7-1.mp3","ref":[7,1258865,1278927]},{"name":"ﾋﾟｱﾉ 1-6.mp3","ref":[7,1278927,1298989]},{"name":"ﾋﾟｱﾉ 1-5.mp3","ref":[7,1298989,1319051]},{"name":"ﾋﾟｱﾉ 1-4.mp3","ref":[7,1319051,1339113]},{"name":"ﾄﾞﾗﾑ C2C# symbal.mp3","ref":[7,1339113,1359175]},{"name":"ﾄﾗﾝﾍﾟｯﾄ　5-3-1.mp3","ref":[7,1359175,1379237]},{"name":"square 2-4.mp3","ref":[7,1379237,1399299]},{"name":"square 81-5.mp3","ref":[7,1399299,1419361]},{"name":"ﾋﾟｱﾉ 1-2.mp3","ref":[7,1419361,1439423]},{"name":"ﾋﾟｱﾉ 2-2.mp3","ref":[7,1439423,1459485]},{"name":"ﾋﾟｱﾉ 2-1.mp3","ref":[8,0,20062]},{"name":"ﾋﾟｱﾉ 1-8-2.mp3","ref":[8,20062,40124]},{"name":"ﾋﾟｱﾉ 1-1.mp3","ref":[8,40124,60186]},{"name":"ｶﾘｵﾍﾟ　45-2.mp3","ref":[8,60186,79830]},{"name":"ｶﾘｵﾍﾟ　45-3.mp3","ref":[8,79830,99474]},{"name":"ｶﾘｵﾍﾟ　45-4.mp3","ref":[8,99474,119118]},{"name":"ｶﾘｵﾍﾟ　46-1.mp3","ref":[8,119118,138762]},{"name":"ｶﾘｵﾍﾟ　46-2.mp3","ref":[8,138762,158406]},{"name":"ｶﾘｵﾍﾟ　46-3.mp3","ref":[8,158406,178050]},{"name":"ｶﾘｵﾍﾟ　46-4.mp3","ref":[8,178050,197694]},{"name":"ｶﾘｵﾍﾟ　47-1.mp3","ref":[8,197694,217338]},{"name":"square 39-4-2.mp3","ref":[8,217338,236982]},{"name":"ﾊｰﾌﾟ　C3G.mp3","ref":[8,236982,256208]},{"name":"ﾊｰﾌﾟ　C5A.mp3","ref":[8,256208,275434]},{"name":"ﾊｰﾌﾟ　C5C#.mp3","ref":[8,275434,294660]},{"name":"ﾊｰﾌﾟ　C5D.mp3","ref":[8,294660,313886]},{"name":"ﾊｰﾌﾟ　C5E.mp3","ref":[8,313886,333112]},{"name":"ﾊｰﾌﾟ　C5F#.mp3","ref":[8,333112,352338]},{"name":"ﾊｰﾌﾟ　C5G.mp3","ref":[8,352338,371564]},{"name":"ﾊｰﾌﾟ　C6A.mp3","ref":[8,371564,390790]},{"name":"ﾊｰﾌﾟ　C4D.mp3","ref":[8,390790,410016]},{"name":"ﾊｰﾌﾟ　C4A#.mp3","ref":[8,410016,429242]},{"name":"ﾊｰﾌﾟ　C4E.mp3","ref":[8,429242,448468]},{"name":"ﾊｰﾌﾟ　C6C#.mp3","ref":[8,448468,467694]},{"name":"ﾊｰﾌﾟ　C4F#.mp3","ref":[8,467694,486920]},{"name":"ﾊｰﾌﾟ　C4A.mp3","ref":[8,486920,506146]},{"name":"ﾊｰﾌﾟ　C6E.mp3","ref":[8,506146,525372]},{"name":"ﾊｰﾌﾟ　C1A.mp3","ref":[8,525372,544598]},{"name":"ﾊｰﾌﾟ　C7A.mp3","ref":[8,544598,563824]},{"name":"ﾊｰﾌﾟ　C7C#.mp3","ref":[8,563824,583050]},{"name":"ﾊｰﾌﾟ　C7E.mp3","ref":[8,583050,602276]},{"name":"ﾊｰﾌﾟ　C4G.mp3","ref":[8,602276,621502]},{"name":"ﾊｰﾌﾟ　C3A.mp3","ref":[8,621502,640728]},{"name":"ﾊｰﾌﾟ　C2G.mp3","ref":[8,640728,659954]},{"name":"ﾊｰﾌﾟ　C2F#.mp3","ref":[8,659954,679180]},{"name":"ﾊｰﾌﾟ　C2E.mp3","ref":[8,679180,698406]},{"name":"ﾊｰﾌﾟ　C2D.mp3","ref":[8,698406,717632]},{"name":"ﾊｰﾌﾟ　C2B.mp3","ref":[8,717632,736858]},{"name":"ﾊｰﾌﾟ　C2A.mp3","ref":[8,736858,756084]},{"name":"ﾊｰﾌﾟ　C2A#.mp3","ref":[8,756084,775310]},{"name":"ﾊｰﾌﾟ　C3A#.mp3","ref":[8,775310,794536]},{"name":"ﾊｰﾌﾟ　C3B.mp3","ref":[8,794536,813762]},{"name":"ﾊｰﾌﾟ　C3C#.mp3","ref":[8,813762,832988]},{"name":"ﾊｰﾌﾟ　C3E.mp3","ref":[8,832988,852214]},{"name":"ﾊｰﾌﾟ　C3F#.mp3","ref":[8,852214,871440]},{"name":"ﾊｰﾌﾟ　C4B.mp3","ref":[8,871440,890666]},{"name":"ﾊｰﾌﾟ　C4C#.mp3","ref":[8,890666,909892]},{"name":"ﾊｰﾌﾟ　C4C.mp3","ref":[8,909892,929118]},{"name":"ｶﾘｵﾍﾟ　44-4.mp3","ref":[8,929118,947926]},{"name":"ｶﾘｵﾍﾟ　42-1.mp3","ref":[8,947926,966734]},{"name":"ﾋﾟｱﾉ 41-11.mp3","ref":[8,966734,985542]},{"name":"triangle 33-4.mp3","ref":[8,985542,1004350]},{"name":"ｶﾘｵﾍﾟ　44-1.mp3","ref":[8,1004350,1023158]},{"name":"triangle 34-1.mp3","ref":[8,1023158,1041966]},{"name":"triangle 34-2.mp3","ref":[8,1041966,1060774]},{"name":"triangle 34-3.mp3","ref":[8,1060774,1079582]},{"name":"triangle 34-4.mp3","ref":[8,1079582,1098390]},{"name":"ｶﾘｵﾍﾟ　44-2.mp3","ref":[8,1098390,1117198]},{"name":"ｶﾘｵﾍﾟ　44-3.mp3","ref":[8,1117198,1136006]},{"name":"ﾄﾗﾝﾍﾟｯﾄ　81-2-2.mp3","ref":[8,1136006,1153978]},{"name":"square 1-4.mp3","ref":[8,1153978,1171950]},{"name":"square 1-3.mp3","ref":[8,1171950,1189922]},{"name":"square 1-2.mp3","ref":[8,1189922,1207894]},{"name":"square 4-1.mp3","ref":[8,1207894,1225866]},{"name":"square 1-7.mp3","ref":[8,1225866,1243838]},{"name":"ﾄﾗﾝﾍﾟｯﾄ　81-2-1.mp3","ref":[8,1243838,1261810]},{"name":"ｱｺｰﾃﾞｨｵﾝ 52-1.mp3","ref":[8,1261810,1279782]},{"name":"square 6-4.mp3","ref":[8,1279782,1297754]},{"name":"square 1-5.mp3","ref":[8,1297754,1315726]},{"name":"square 1-6.mp3","ref":[8,1315726,1333698]},{"name":"triangle 86-4.mp3","ref":[8,1333698,1351252]},{"name":"triangle 83-2.mp3","ref":[8,1351252,1368806]},{"name":"triangle 84-1.mp3","ref":[8,1368806,1386360]},{"name":"triangle 84-2.mp3","ref":[8,1386360,1403914]},{"name":"triangle 85-1.mp3","ref":[8,1403914,1421468]},{"name":"triangle 85-2.mp3","ref":[8,1421468,1439022]},{"name":"triangle 85-3.mp3","ref":[8,1439022,1456576]},{"name":"triangle 85-4.mp3","ref":[8,1456576,1474130]},{"name":"triangle 86-1.mp3","ref":[9,0,17554]},{"name":"triangle 86-2.mp3","ref":[9,17554,35108]},{"name":"triangle 86-3.mp3","ref":[9,35108,52662]},{"name":"triangle 83-1.mp3","ref":[9,52662,70216]},{"name":"ﾋﾟｱﾉ 42-8.mp3","ref":[9,70216,86934]},{"name":"square 3-3.mp3","ref":[9,86934,103652]},{"name":"square 3-4.mp3","ref":[9,103652,120370]},{"name":"square 3-5.mp3","ref":[9,120370,137088]},{"name":"square 2-2.mp3","ref":[9,137088,153806]},{"name":"ｶﾘｵﾍﾟ　43-3.mp3","ref":[9,153806,170524]},{"name":"ﾋﾟｱﾉ 42-9.mp3","ref":[9,170524,187242]},{"name":"ﾋﾟｱﾉ 42-7-2.mp3","ref":[9,187242,203960]},{"name":"square 3-2.mp3","ref":[9,203960,220678]},{"name":"ﾋﾟｱﾉ 42-5.mp3","ref":[9,220678,237396]},{"name":"ﾋﾟｱﾉ 42-6.mp3","ref":[9,237396,254114]},{"name":"ﾋﾟｱﾉ 42-7-1.mp3","ref":[9,254114,270832]},{"name":"ｶﾘｵﾍﾟ　43-4.mp3","ref":[9,270832,287550]},{"name":"25% 11_-2-1.mp3","ref":[9,287550,303850]},{"name":"25% 11_-1-2.mp3","ref":[9,303850,320150]},{"name":"25% 11_-1-1.mp3","ref":[9,320150,336450]},{"name":"25% 9_-2-1.mp3","ref":[9,336450,352750]},{"name":"25% 9_-2-2.mp3","ref":[9,352750,369050]},{"name":"25% 9__D.mp3","ref":[9,369050,385350]},{"name":"25% 13_-1-1.mp3","ref":[9,385350,401650]},{"name":"12.5% 60-3.mp3","ref":[9,401650,417950]},{"name":"12.5% 62-2.mp3","ref":[9,417950,434250]},{"name":"12.5% 62-3.mp3","ref":[9,434250,450550]},{"name":"12.5% 64-1.mp3","ref":[9,450550,466850]},{"name":"12.5% 65-1.mp3","ref":[9,466850,483150]},{"name":"triangle 32-4.mp3","ref":[9,483150,499450]},{"name":"25% 9_-1-1.mp3","ref":[9,499450,515750]},{"name":"25% 9_-1-2.mp3","ref":[9,515750,532050]},{"name":"square 39-1-1.mp3","ref":[9,532050,548350]},{"name":"25% 13_-2-2.mp3","ref":[9,548350,564650]},{"name":"25% 13_-2-1.mp3","ref":[9,564650,580950]},{"name":"25% 13_-1-2.mp3","ref":[9,580950,597250]},{"name":"25% 11_-2-2.mp3","ref":[9,597250,613550]},{"name":"square 39-1-2.mp3","ref":[9,613550,629850]},{"name":"square 6-5.mp3","ref":[9,629850,645732]},{"name":"square 7-1.mp3","ref":[9,645732,661614]},{"name":"ﾄﾞﾗﾑ snare 105%.mp3","ref":[9,661614,677078]},{"name":"ﾄﾞﾗﾑ snare 90%.mp3","ref":[9,677078,692542]},{"name":"ﾄﾗﾝﾍﾟｯﾄ　5-4.mp3","ref":[9,692542,708006]},{"name":"square 6-3.mp3","ref":[9,708006,723470]},{"name":"square 6-2.mp3","ref":[9,723470,738934]},{"name":"ﾄﾗﾝﾍﾟｯﾄ　6-2-2.mp3","ref":[9,738934,754398]},{"name":"ﾄﾗﾝﾍﾟｯﾄ　6-2-1.mp3","ref":[9,754398,769862]},{"name":"square 6-1.mp3","ref":[9,769862,785326]},{"name":"ﾄﾗﾝﾍﾟｯﾄ　5-7-2.mp3","ref":[9,785326,800790]},{"name":"ﾄﾗﾝﾍﾟｯﾄ　5-5-1.mp3","ref":[9,800790,816254]},{"name":"ﾄﾗﾝﾍﾟｯﾄ　5-5-2.mp3","ref":[9,816254,831718]},{"name":"ﾄﾗﾝﾍﾟｯﾄ　5-7-1.mp3","ref":[9,831718,847182]},{"name":"ﾄﾗﾝﾍﾟｯﾄ　5-6-1.mp3","ref":[9,847182,862646]},{"name":"ﾄﾞﾗﾑ snare 125%.mp3","ref":[9,862646,878110]},{"name":"square 5-1.mp3","ref":[9,878110,893574]},{"name":"ﾄﾗﾝﾍﾟｯﾄ　5-1-1.mp3","ref":[9,893574,909038]},{"name":"ﾄﾗﾝﾍﾟｯﾄ　5-1-2.mp3","ref":[9,909038,924502]},{"name":"ﾄﾗﾝﾍﾟｯﾄ　5-2-1.mp3","ref":[9,924502,939966]},{"name":"ﾄﾗﾝﾍﾟｯﾄ　5-6-2.mp3","ref":[9,939966,955430]},{"name":"ﾄﾗﾝﾍﾟｯﾄ　5-2-2.mp3","ref":[9,955430,970894]},{"name":"ﾄﾞﾗﾑ snare 75%.mp3","ref":[9,970894,986358]},{"name":"square 5-4.mp3","ref":[9,986358,1001822]},{"name":"square 4-4.mp3","ref":[9,1001822,1017286]},{"name":"square 4-2.mp3","ref":[9,1017286,1032750]},{"name":"square 4-3.mp3","ref":[9,1032750,1048214]},{"name":"ﾋﾟｱﾉ 43-4-2.mp3","ref":[9,1048214,1062842]},{"name":"ｶﾘｵﾍﾟ　43-2.mp3","ref":[9,1062842,1077470]},{"name":"ﾋﾟｱﾉ 44-10.mp3","ref":[9,1077470,1092098]},{"name":"ﾋﾟｱﾉ 44-11.mp3","ref":[9,1092098,1106726]},{"name":"ﾋﾟｱﾉ 44-12.mp3","ref":[9,1106726,1121354]},{"name":"ﾋﾟｱﾉ 44-13.mp3","ref":[9,1121354,1135982]},{"name":"ｶﾘｵﾍﾟ　42-4.mp3","ref":[9,1135982,1150610]},{"name":"ｶﾘｵﾍﾟ　42-3.mp3","ref":[9,1150610,1165238]},{"name":"ﾋﾟｱﾉ 44-9.mp3","ref":[9,1165238,1179866]},{"name":"ﾋﾟｱﾉ 44-8.mp3","ref":[9,1179866,1194494]},{"name":"ﾋﾟｱﾉ 44-7.mp3","ref":[9,1194494,1209122]},{"name":"ﾋﾟｱﾉ 44-18.mp3","ref":[9,1209122,1223750]},{"name":"ﾋﾟｱﾉ 44-17.mp3","ref":[9,1223750,1238378]},{"name":"ﾋﾟｱﾉ 44-16.mp3","ref":[9,1238378,1253006]},{"name":"ﾋﾟｱﾉ 44-15.mp3","ref":[9,1253006,1267634]},{"name":"ﾋﾟｱﾉ 43-4-1.mp3","ref":[9,1267634,1282262]},{"name":"ﾋﾟｱﾉ 44-14.mp3","ref":[9,1282262,1296890]},{"name":"25% 9-1.mp3","ref":[9,1296890,1310682]},{"name":"25% 62-2-1.mp3","ref":[9,1310682,1324474]},{"name":"25% 63-2-1.mp3","ref":[9,1324474,1338266]},{"name":"25% 63-2-2.mp3","ref":[9,1338266,1352058]},{"name":"triangle 35-1.mp3","ref":[9,1352058,1365850]},{"name":"25% 62-1.mp3","ref":[9,1365850,1379642]},{"name":"25% 61-2-2.mp3","ref":[9,1379642,1393434]},{"name":"25% 63-1.mp3","ref":[9,1393434,1407226]},{"name":"25% 9-2.mp3","ref":[9,1407226,1421018]},{"name":"triangle 36-1.mp3","ref":[9,1421018,1434810]},{"name":"25% 61-2-1.mp3","ref":[9,1434810,1448602]},{"name":"25% 61-1-2.mp3","ref":[9,1448602,1462394]},{"name":"25% 61-1-1.mp3","ref":[10,0,13792]},{"name":"25% 62-2-2.mp3","ref":[10,13792,27584]},{"name":"ﾃｨﾝﾊﾟﾆ C1D.mp3","ref":[10,27584,40958]},{"name":"ﾃｨﾝﾊﾟﾆ C1A#.mp3","ref":[10,40958,54332]},{"name":"ﾃｨﾝﾊﾟﾆ C1F#.mp3","ref":[10,54332,67706]},{"name":"ﾃｨﾝﾊﾟﾆ C1G#.mp3","ref":[10,67706,81080]},{"name":"ﾃｨﾝﾊﾟﾆ C1G.mp3","ref":[10,81080,94454]},{"name":"ﾃｨﾝﾊﾟﾆ C1B.mp3","ref":[10,94454,107828]},{"name":"ﾃｨﾝﾊﾟﾆ C0A.mp3","ref":[10,107828,121202]},{"name":"ﾃｨﾝﾊﾟﾆ C1E.mp3","ref":[10,121202,134576]},{"name":"ﾃｨﾝﾊﾟﾆ C1A.mp3","ref":[10,134576,147950]},{"name":"ﾃｨﾝﾊﾟﾆ C1C#.mp3","ref":[10,147950,161324]},{"name":"square 3-6.mp3","ref":[10,161324,174280]},{"name":"square 5-6.mp3","ref":[10,174280,187236]},{"name":"square 5-5.mp3","ref":[10,187236,200192]},{"name":"square 5-3.mp3","ref":[10,200192,213148]},{"name":"square 5-2.mp3","ref":[10,213148,226104]},{"name":"square 39-5.mp3","ref":[10,226104,239060]},{"name":"square 3-1.mp3","ref":[10,239060,252016]},{"name":"triangle 98-2.mp3","ref":[10,252016,264554]},{"name":"ｶﾘｵﾍﾟ　41-2.mp3","ref":[10,264554,277092]},{"name":"ｶﾘｵﾍﾟ　41-1.mp3","ref":[10,277092,289630]},{"name":"ｶﾘｵﾍﾟ　41-3.mp3","ref":[10,289630,302168]},{"name":"ﾋﾟｱﾉ 41-12.mp3","ref":[10,302168,314706]},{"name":"ﾋﾟｱﾉ 42-10.mp3","ref":[10,314706,327244]},{"name":"ﾋﾟｱﾉ 42-11.mp3","ref":[10,327244,339782]},{"name":"ﾋﾟｱﾉ 42-12.mp3","ref":[10,339782,352320]},{"name":"ﾋﾟｱﾉ 42-13.mp3","ref":[10,352320,364858]},{"name":"ﾋﾟｱﾉ 42-14.mp3","ref":[10,364858,377396]},{"name":"ﾋﾟｱﾉ 42-15.mp3","ref":[10,377396,389934]},{"name":"ﾄﾗﾝﾍﾟｯﾄ　81-1-1.mp3","ref":[10,389934,402054]},{"name":"ﾄﾗﾝﾍﾟｯﾄ　81-1-2.mp3","ref":[10,402054,414174]},{"name":"ﾄﾗﾝﾍﾟｯﾄ　88-1-2.mp3","ref":[10,414174,426294]},{"name":"ﾄﾗﾝﾍﾟｯﾄ　50_-3.mp3","ref":[10,426294,438414]},{"name":"triangle 89-3.mp3","ref":[10,438414,450534]},{"name":"ﾄﾗﾝﾍﾟｯﾄ　88-1-1.mp3","ref":[10,450534,462654]},{"name":"ﾄﾗﾝﾍﾟｯﾄ　50_-1.mp3","ref":[10,462654,474774]},{"name":"square 7-2.mp3","ref":[10,474774,486894]},{"name":"triangle 89-2.mp3","ref":[10,486894,499014]},{"name":"triangle 89-1.mp3","ref":[10,499014,511134]},{"name":"triangle 87-4.mp3","ref":[10,511134,523254]},{"name":"triangle 87-3.mp3","ref":[10,523254,535374]},{"name":"ﾛｯｸｵﾙｶﾞﾝ 47-6.mp3","ref":[10,535374,547494]},{"name":"triangle 87-2.mp3","ref":[10,547494,559614]},{"name":"ｱｺｰﾃﾞｨｵﾝ 50-1.mp3","ref":[10,559614,571734]},{"name":"ｱｺｰﾃﾞｨｵﾝ 50-2.mp3","ref":[10,571734,583854]},{"name":"25% 55-bass2.mp3","ref":[10,583854,595974]},{"name":"25% 55-bass1.mp3","ref":[10,595974,608094]},{"name":"25% 54-bass2.mp3","ref":[10,608094,620214]},{"name":"25% 54-bass1.mp3","ref":[10,620214,632334]},{"name":"25% 53-bass2.mp3","ref":[10,632334,644454]},{"name":"25% 53-bass1.mp3","ref":[10,644454,656574]},{"name":"ｱｺｰﾃﾞｨｵﾝ 50-3.mp3","ref":[10,656574,668694]},{"name":"ﾄﾗﾝﾍﾟｯﾄ　49_-1.mp3","ref":[10,668694,680814]},{"name":"triangle 87-1.mp3","ref":[10,680814,692934]},{"name":"triangle 82-3.mp3","ref":[10,692934,705054]},{"name":"triangle 82-2.mp3","ref":[10,705054,717174]},{"name":"triangle 82-1.mp3","ref":[10,717174,729294]},{"name":"ﾄﾗﾝﾍﾟｯﾄ　52_-2.mp3","ref":[10,729294,741414]},{"name":"square 39-6.mp3","ref":[10,741414,753116]},{"name":"triangle 31-2.mp3","ref":[10,753116,764400]},{"name":"12.5% 16-4.mp3","ref":[10,764400,775684]},{"name":"triangle 26-bass.mp3","ref":[10,775684,786968]},{"name":"12.5% 16-5.mp3","ref":[10,786968,798252]},{"name":"12.5% 16-6.mp3","ref":[10,798252,809536]},{"name":"12.5% 16-7.mp3","ref":[10,809536,820820]},{"name":"triangle 27-bass.mp3","ref":[10,820820,832104]},{"name":"12.5% 16-8.mp3","ref":[10,832104,843388]},{"name":"12.5% 16-9.mp3","ref":[10,843388,854672]},{"name":"12.5% 23-2.mp3","ref":[10,854672,865956]},{"name":"triangle 28-1.mp3","ref":[10,865956,877240]},{"name":"triangle 28-2.mp3","ref":[10,877240,888524]},{"name":"triangle 28-3.mp3","ref":[10,888524,899808]},{"name":"triangle 28-4.mp3","ref":[10,899808,911092]},{"name":"triangle 28-bass.mp3","ref":[10,911092,922376]},{"name":"12.5% 12-4.mp3","ref":[10,922376,933660]},{"name":"triangle 29-1.mp3","ref":[10,933660,944944]},{"name":"triangle 29-2.mp3","ref":[10,944944,956228]},{"name":"triangle 29-3.mp3","ref":[10,956228,967512]},{"name":"triangle 29-4.mp3","ref":[10,967512,978796]},{"name":"triangle 29-5.mp3","ref":[10,978796,990080]},{"name":"triangle 29-6.mp3","ref":[10,990080,1001364]},{"name":"triangle 29-bass.mp3","ref":[10,1001364,1012648]},{"name":"12.5% 12-1.mp3","ref":[10,1012648,1023932]},{"name":"triangle 30-1.mp3","ref":[10,1023932,1035216]},{"name":"triangle 30-2.mp3","ref":[10,1035216,1046500]},{"name":"triangle 30-3.mp3","ref":[10,1046500,1057784]},{"name":"triangle 30-4.mp3","ref":[10,1057784,1069068]},{"name":"triangle 30-5.mp3","ref":[10,1069068,1080352]},{"name":"triangle 30-6.mp3","ref":[10,1080352,1091636]},{"name":"triangle 30-bass.mp3","ref":[10,1091636,1102920]},{"name":"12.5% 14-1.mp3","ref":[10,1102920,1114204]},{"name":"triangle 31-1.mp3","ref":[10,1114204,1125488]},{"name":"12.5% 12-2.mp3","ref":[10,1125488,1136772]},{"name":"triangle 31-3.mp3","ref":[10,1136772,1148056]},{"name":"triangle 31-4.mp3","ref":[10,1148056,1159340]},{"name":"triangle 31-5.mp3","ref":[10,1159340,1170624]},{"name":"triangle 31-bass.mp3","ref":[10,1170624,1181908]},{"name":"noise 100%.mp3","ref":[10,1181908,1193192]},{"name":"triangle 32-1.mp3","ref":[10,1193192,1204476]},{"name":"triangle 32-2.mp3","ref":[10,1204476,1215760]},{"name":"triangle 32-3.mp3","ref":[10,1215760,1227044]},{"name":"noise 50%.mp3","ref":[10,1227044,1238328]},{"name":"triangle 32-bass.mp3","ref":[10,1238328,1249612]},{"name":"noise 65%.mp3","ref":[10,1249612,1260896]},{"name":"triangle 33-1.mp3","ref":[10,1260896,1272180]},{"name":"triangle 33-2.mp3","ref":[10,1272180,1283464]},{"name":"triangle 33-3.mp3","ref":[10,1283464,1294748]},{"name":"noise 75%.mp3","ref":[10,1294748,1306032]},{"name":"triangle 33-bass.mp3","ref":[10,1306032,1317316]},{"name":"noise long.mp3","ref":[10,1317316,1328600]},{"name":"12.5% 14-2.mp3","ref":[10,1328600,1339884]},{"name":"12.5% 14-3.mp3","ref":[10,1339884,1351168]},{"name":"12.5% 14-4.mp3","ref":[10,1351168,1362452]},{"name":"12.5% 15-1.mp3","ref":[10,1362452,1373736]},{"name":"triangle 34-bass.mp3","ref":[10,1373736,1385020]},{"name":"12.5% 12-3.mp3","ref":[10,1385020,1396304]},{"name":"12.5% 16-1.mp3","ref":[10,1396304,1407588]},{"name":"12.5% 16-10.mp3","ref":[10,1407588,1418872]},{"name":"triangle 25-bass.mp3","ref":[10,1418872,1430156]},{"name":"triangle 35-4.mp3","ref":[10,1430156,1441440]},{"name":"triangle 35-5.mp3","ref":[10,1441440,1452724]},{"name":"triangle 35-6.mp3","ref":[10,1452724,1464008]},{"name":"triangle 35-bass.mp3","ref":[11,0,11284]},{"name":"12.5% 16-11.mp3","ref":[11,11284,22568]},{"name":"square 39-4-1.mp3","ref":[11,22568,33852]},{"name":"triangle 36-2.mp3","ref":[11,33852,45136]},{"name":"triangle 36-3.mp3","ref":[11,45136,56420]},{"name":"triangle 36-4.mp3","ref":[11,56420,67704]},{"name":"triangle 36-bass.mp3","ref":[11,67704,78988]},{"name":"12.5% 16-12.mp3","ref":[11,78988,90272]},{"name":"triangle 37-1.mp3","ref":[11,90272,101556]},{"name":"ｼﾝｾﾄﾞﾗﾑ bass.mp3","ref":[11,101556,112840]},{"name":"ｼﾝｾﾄﾞﾗﾑ bass2.mp3","ref":[11,112840,124124]},{"name":"ｼﾝｾﾄﾞﾗﾑ snare.mp3","ref":[11,124124,135408]},{"name":"ｼﾝｾﾄﾞﾗﾑ snare2.mp3","ref":[11,135408,146692]},{"name":"triangle 37-2.mp3","ref":[11,146692,157976]},{"name":"12.5% 16-13.mp3","ref":[11,157976,169260]},{"name":"12.5% 16-2.mp3","ref":[11,169260,180544]},{"name":"12.5% 16-3.mp3","ref":[11,180544,191828]},{"name":"12.5% 65-3.mp3","ref":[11,191828,202694]},{"name":"25% 60-1.mp3","ref":[11,202694,213560]},{"name":"ｼﾝｾﾄﾞﾗﾑ symbal.mp3","ref":[11,213560,224426]},{"name":"ｶﾘｵﾍﾟ　45-1.mp3","ref":[11,224426,235292]},{"name":"ｱｺｰﾃﾞｨｵﾝ 51-5.mp3","ref":[11,235292,246158]},{"name":"ｱｺｰﾃﾞｨｵﾝ 51-4.mp3","ref":[11,246158,257024]},{"name":"ｱｺｰﾃﾞｨｵﾝ 51-3.mp3","ref":[11,257024,267890]},{"name":"25% 59-1.mp3","ref":[11,267890,278756]},{"name":"25% 59-2-1.mp3","ref":[11,278756,289622]},{"name":"25% 59-2-2.mp3","ref":[11,289622,300488]},{"name":"12.5% 61-1.mp3","ref":[11,300488,311354]},{"name":"12.5% 61-2.mp3","ref":[11,311354,322220]},{"name":"12.5% 62-1.mp3","ref":[11,322220,333086]},{"name":"12.5% 63-1.mp3","ref":[11,333086,343952]},{"name":"12.5% 63-2.mp3","ref":[11,343952,354818]},{"name":"12.5% 63-3.mp3","ref":[11,354818,365684]},{"name":"12.5% 63-4.mp3","ref":[11,365684,376550]},{"name":"12.5% 63-5.mp3","ref":[11,376550,387416]},{"name":"12.5% 65-2.mp3","ref":[11,387416,398282]},{"name":"ｼﾝｾﾄﾞﾗﾑ symbal2.mp3","ref":[11,398282,409148]},{"name":"12.5% 65-4.mp3","ref":[11,409148,420014]},{"name":"12.5% 66-1.mp3","ref":[11,420014,430880]},{"name":"12.5% 66-2.mp3","ref":[11,430880,441746]},{"name":"12.5% 66-3.mp3","ref":[11,441746,452612]},{"name":"12.5% 67-1.mp3","ref":[11,452612,463478]},{"name":"12.5% 67-2.mp3","ref":[11,463478,474344]},{"name":"12.5% 67-3.mp3","ref":[11,474344,485210]},{"name":"12.5% 68-1.mp3","ref":[11,485210,496076]},{"name":"12.5% 68-2.mp3","ref":[11,496076,506942]},{"name":"12.5% 68-3.mp3","ref":[11,506942,517808]},{"name":"12.5% 69-1.mp3","ref":[11,517808,528674]},{"name":"12.5% 69-2.mp3","ref":[11,528674,539540]},{"name":"12.5% 69-3.mp3","ref":[11,539540,550406]},{"name":"12.5% 70-1.mp3","ref":[11,550406,561272]},{"name":"12.5% 70-2.mp3","ref":[11,561272,572138]},{"name":"12.5% 72-2.mp3","ref":[11,572138,583004]},{"name":"25% 60-2-2.mp3","ref":[11,583004,593870]},{"name":"25% 60-2-1.mp3","ref":[11,593870,604736]},{"name":"triangle 5-15.mp3","ref":[11,604736,615185]},{"name":"ﾛｯｸｵﾙｶﾞﾝ 48-14.mp3","ref":[11,615185,625634]},{"name":"ﾛｯｸｵﾙｶﾞﾝ 48-13.mp3","ref":[11,625634,636083]},{"name":"triangle 6-9.mp3","ref":[11,636083,646532]},{"name":"triangle 6-8.mp3","ref":[11,646532,656981]},{"name":"triangle 6-7.mp3","ref":[11,656981,667430]},{"name":"triangle 6-6.mp3","ref":[11,667430,677879]},{"name":"triangle 6-5.mp3","ref":[11,677879,688328]},{"name":"triangle 6-4.mp3","ref":[11,688328,698777]},{"name":"triangle 6-3.mp3","ref":[11,698777,709226]},{"name":"triangle 6-2.mp3","ref":[11,709226,719675]},{"name":"triangle 6-12.mp3","ref":[11,719675,730124]},{"name":"triangle 6-11.mp3","ref":[11,730124,740573]},{"name":"triangle 6-10.mp3","ref":[11,740573,751022]},{"name":"triangle 6-1.mp3","ref":[11,751022,761471]},{"name":"triangle 5-9.mp3","ref":[11,761471,771920]},{"name":"triangle 5-8.mp3","ref":[11,771920,782369]},{"name":"triangle 5-7.mp3","ref":[11,782369,792818]},{"name":"triangle 5-6.mp3","ref":[11,792818,803267]},{"name":"triangle 5-5.mp3","ref":[11,803267,813716]},{"name":"triangle 5-24.mp3","ref":[11,813716,824165]},{"name":"triangle 5-23.mp3","ref":[11,824165,834614]},{"name":"triangle 5-22.mp3","ref":[11,834614,845063]},{"name":"triangle 5-21.mp3","ref":[11,845063,855512]},{"name":"triangle 5-20.mp3","ref":[11,855512,865961]},{"name":"triangle 5-19.mp3","ref":[11,865961,876410]},{"name":"triangle 5-18.mp3","ref":[11,876410,886859]},{"name":"triangle 5-17.mp3","ref":[11,886859,897308]},{"name":"triangle 5-16.mp3","ref":[11,897308,907757]},{"name":"ﾛｯｸｵﾙｶﾞﾝ 48-8.mp3","ref":[11,907757,918206]},{"name":"triangle 5-14.mp3","ref":[11,918206,928655]},{"name":"triangle 5-13.mp3","ref":[11,928655,939104]},{"name":"triangle 5-12.mp3","ref":[11,939104,949553]},{"name":"triangle 5-11.mp3","ref":[11,949553,960002]},{"name":"triangle 5-10.mp3","ref":[11,960002,970451]},{"name":"ﾛｯｸｵﾙｶﾞﾝ 48-12.mp3","ref":[11,970451,980900]},{"name":"ｱｺｰﾃﾞｨｵﾝ 50-4.mp3","ref":[11,980900,991349]},{"name":"ｱｺｰﾃﾞｨｵﾝ 49-3.mp3","ref":[11,991349,1001798]},{"name":"ｱｺｰﾃﾞｨｵﾝ 49-2.mp3","ref":[11,1001798,1012247]},{"name":"ｱｺｰﾃﾞｨｵﾝ 49-1.mp3","ref":[11,1012247,1022696]},{"name":"25% 4-8.mp3","ref":[11,1022696,1033145]},{"name":"25% 4-7.mp3","ref":[11,1033145,1043594]},{"name":"25% 4-6.mp3","ref":[11,1043594,1054043]},{"name":"25% 4-5.mp3","ref":[11,1054043,1064492]},{"name":"25% 4-4.mp3","ref":[11,1064492,1074941]},{"name":"25% 58-2-2.mp3","ref":[11,1074941,1085390]},{"name":"ﾛｯｸｵﾙｶﾞﾝ 48-2.mp3","ref":[11,1085390,1095839]},{"name":"ﾛｯｸｵﾙｶﾞﾝ 48-9.mp3","ref":[11,1095839,1106288]},{"name":"ﾛｯｸｵﾙｶﾞﾝ 48-7.mp3","ref":[11,1106288,1116737]},{"name":"ﾛｯｸｵﾙｶﾞﾝ 48-11.mp3","ref":[11,1116737,1127186]},{"name":"ﾛｯｸｵﾙｶﾞﾝ 48-10.mp3","ref":[11,1127186,1137635]},{"name":"ﾛｯｸｵﾙｶﾞﾝ 48-1.mp3","ref":[11,1137635,1148084]},{"name":"ﾛｯｸｵﾙｶﾞﾝ 48-6.mp3","ref":[11,1148084,1158533]},{"name":"ｶﾘｵﾍﾟ　42-2.mp3","ref":[11,1158533,1168982]},{"name":"25% 4-3.mp3","ref":[11,1168982,1179431]},{"name":"25% 4-2.mp3","ref":[11,1179431,1189880]},{"name":"25% 3-1.mp3","ref":[11,1189880,1200329]},{"name":"25% 3-10.mp3","ref":[11,1200329,1210778]},{"name":"25% 3-11.mp3","ref":[11,1210778,1221227]},{"name":"25% 3-12.mp3","ref":[11,1221227,1231676]},{"name":"25% 3-2.mp3","ref":[11,1231676,1242125]},{"name":"25% 3-3.mp3","ref":[11,1242125,1252574]},{"name":"25% 3-4.mp3","ref":[11,1252574,1263023]},{"name":"25% 3-5.mp3","ref":[11,1263023,1273472]},{"name":"25% 3-6.mp3","ref":[11,1273472,1283921]},{"name":"25% 3-7.mp3","ref":[11,1283921,1294370]},{"name":"25% 3-8.mp3","ref":[11,1294370,1304819]},{"name":"25% 3-9.mp3","ref":[11,1304819,1315268]},{"name":"square 3-8.mp3","ref":[11,1315268,1325717]},{"name":"square 3-7.mp3","ref":[11,1325717,1336166]},{"name":"square 2-1.mp3","ref":[11,1336166,1346615]},{"name":"25% 4-1.mp3","ref":[11,1346615,1357064]},{"name":"25% 4-10.mp3","ref":[11,1357064,1367513]},{"name":"25% 4-11.mp3","ref":[11,1367513,1377962]},{"name":"25% 4-12.mp3","ref":[11,1377962,1388411]},{"name":"25% 4-13.mp3","ref":[11,1388411,1398860]},{"name":"25% 4-14.mp3","ref":[11,1398860,1409309]},{"name":"25% 4-15.mp3","ref":[11,1409309,1419758]},{"name":"ﾛｯｸｵﾙｶﾞﾝ 48-5.mp3","ref":[11,1419758,1430207]},{"name":"ﾛｯｸｵﾙｶﾞﾝ 48-4.mp3","ref":[11,1430207,1440656]},{"name":"ﾛｯｸｵﾙｶﾞﾝ 48-3.mp3","ref":[11,1440656,1451105]},{"name":"25% 4-16.mp3","ref":[11,1451105,1461554]},{"name":"25% 4-9.mp3","ref":[11,1461554,1472003]},{"name":"25% 58-1.mp3","ref":[12,0,10031]},{"name":"triangle 97-5.mp3","ref":[12,10031,19644]},{"name":"triangle 97-1.mp3","ref":[12,19644,29257]},{"name":"triangle 97-3.mp3","ref":[12,29257,38870]},{"name":"triangle 97-4.mp3","ref":[12,38870,48483]},{"name":"25% 58-2-1.mp3","ref":[12,48483,58096]},{"name":"25% 13-2.mp3","ref":[12,58096,67709]},{"name":"triangle 97-2.mp3","ref":[12,67709,77322]},{"name":"triangle 97-6.mp3","ref":[12,77322,86935]},{"name":"triangle 97-7.mp3","ref":[12,86935,96548]},{"name":"triangle 97-8.mp3","ref":[12,96548,106161]},{"name":"triangle 97-9.mp3","ref":[12,106161,115774]},{"name":"25% 14-1.mp3","ref":[12,115774,125387]},{"name":"25% 40-2.mp3","ref":[12,125387,134582]},{"name":"triangle 92-1.mp3","ref":[12,134582,143777]},{"name":"25% 40-8.mp3","ref":[12,143777,152972]},{"name":"25% 40-4.mp3","ref":[12,152972,162167]},{"name":"25% 40-3.mp3","ref":[12,162167,171362]},{"name":"25% 40-1.mp3","ref":[12,171362,180557]},{"name":"triangle 17-3.mp3","ref":[12,180557,188916]},{"name":"ﾛｯｸｵﾙｶﾞﾝ 47-4.mp3","ref":[12,188916,197275]},{"name":"ﾛｯｸｵﾙｶﾞﾝ 47-3.mp3","ref":[12,197275,205634]},{"name":"ﾛｯｸｵﾙｶﾞﾝ 47-2.mp3","ref":[12,205634,213993]},{"name":"ﾛｯｸｵﾙｶﾞﾝ 47-10.mp3","ref":[12,213993,222352]},{"name":"25% 70-1.mp3","ref":[12,222352,230711]},{"name":"25% 70-2.mp3","ref":[12,230711,239070]},{"name":"25% 70-3.mp3","ref":[12,239070,247429]},{"name":"25% 71-1.mp3","ref":[12,247429,255788]},{"name":"ﾛｯｸｵﾙｶﾞﾝ 47-1.mp3","ref":[12,255788,264147]},{"name":"12.5% 58-2.mp3","ref":[12,264147,272506]},{"name":"12.5% 58-3.mp3","ref":[12,272506,280865]},{"name":"ｱｺｰﾃﾞｨｵﾝ 50-5.mp3","ref":[12,280865,289224]},{"name":"12.5% 58-4.mp3","ref":[12,289224,297583]},{"name":"12.5% 59-1.mp3","ref":[12,297583,305942]},{"name":"12.5% 59-2.mp3","ref":[12,305942,314301]},{"name":"ﾛｯｸｵﾙｶﾞﾝ 47-9.mp3","ref":[12,314301,322660]},{"name":"ﾛｯｸｵﾙｶﾞﾝ 47-8.mp3","ref":[12,322660,331019]},{"name":"ﾛｯｸｵﾙｶﾞﾝ 47-7.mp3","ref":[12,331019,339378]},{"name":"12.5% 58-1.mp3","ref":[12,339378,347737]},{"name":"ﾛｯｸｵﾙｶﾞﾝ 47-5.mp3","ref":[12,347737,356096]},{"name":"square 37-1.mp3","ref":[12,356096,364455]},{"name":"square 37-2.mp3","ref":[12,364455,372814]},{"name":"square 37-4.mp3","ref":[12,372814,381173]},{"name":"square 37-5.mp3","ref":[12,381173,389532]},{"name":"square 37-6.mp3","ref":[12,389532,397891]},{"name":"square 37-7.mp3","ref":[12,397891,406250]},{"name":"square 38-1.mp3","ref":[12,406250,414609]},{"name":"square 38-2.mp3","ref":[12,414609,422968]},{"name":"square 38-5.mp3","ref":[12,422968,431327]},{"name":"square 38-6.mp3","ref":[12,431327,439686]},{"name":"square 38-7.mp3","ref":[12,439686,448045]},{"name":"square 39-2.mp3","ref":[12,448045,456404]},{"name":"square 39-3.mp3","ref":[12,456404,464763]},{"name":"triangle 17-1.mp3","ref":[12,464763,473122]},{"name":"25% 13-1.mp3","ref":[12,473122,481481]},{"name":"25% 12-1.mp3","ref":[12,481481,489840]},{"name":"triangle 17-2.mp3","ref":[12,489840,498199]},{"name":"12.5% 59-3.mp3","ref":[12,498199,506558]},{"name":"triangle 17-4.mp3","ref":[12,506558,514917]},{"name":"triangle 17-5.mp3","ref":[12,514917,523276]},{"name":"triangle 17-6.mp3","ref":[12,523276,531635]},{"name":"triangle 25-1.mp3","ref":[12,531635,539994]},{"name":"triangle 25-2.mp3","ref":[12,539994,548353]},{"name":"triangle 25-3.mp3","ref":[12,548353,556712]},{"name":"triangle 25-4.mp3","ref":[12,556712,565071]},{"name":"triangle 25-5.mp3","ref":[12,565071,573430]},{"name":"triangle 26-1.mp3","ref":[12,573430,581789]},{"name":"triangle 26-2.mp3","ref":[12,581789,590148]},{"name":"triangle 26-3.mp3","ref":[12,590148,598507]},{"name":"triangle 26-4.mp3","ref":[12,598507,606866]},{"name":"triangle 26-5.mp3","ref":[12,606866,615225]},{"name":"triangle 26-6.mp3","ref":[12,615225,623584]},{"name":"triangle 27-1.mp3","ref":[12,623584,631943]},{"name":"triangle 35-2.mp3","ref":[12,631943,640302]},{"name":"triangle 35-3.mp3","ref":[12,640302,648661]},{"name":"12.5% 60-1.mp3","ref":[12,648661,657020]},{"name":"12.5% 60-2.mp3","ref":[12,657020,665379]},{"name":"ｱｺｰﾃﾞｨｵﾝ 51-2.mp3","ref":[12,665379,673320]},{"name":"25% 72-3.mp3","ref":[12,673320,681261]},{"name":"25% 72-1.mp3","ref":[12,681261,689202]},{"name":"25% 6-3.mp3","ref":[12,689202,697143]},{"name":"25% 6-2.mp3","ref":[12,697143,705084]},{"name":"25% 6-1.mp3","ref":[12,705084,713025]},{"name":"25% 72-2.mp3","ref":[12,713025,720548]},{"name":"triangle 95-1.mp3","ref":[12,720548,727235]},{"name":"triangle 94-3.mp3","ref":[12,727235,733922]},{"name":"triangle 93-2.mp3","ref":[12,733922,740609]},{"name":"triangle 95-2.mp3","ref":[12,740609,747296]},{"name":"triangle 93-3.mp3","ref":[12,747296,753983]},{"name":"triangle 94-1.mp3","ref":[12,753983,760670]},{"name":"triangle 94-2.mp3","ref":[12,760670,767357]},{"name":"triangle 92-3.mp3","ref":[12,767357,774044]},{"name":"triangle 92-2.mp3","ref":[12,774044,780731]},{"name":"triangle 93-1.mp3","ref":[12,780731,787418]},{"name":"12.5% C3G.mp3","ref":[12,787418,793687]},{"name":"25% 40-9.mp3","ref":[12,793687,799956]},{"name":"25% 40-12.mp3","ref":[12,799956,806225]},{"name":"25% 40-13.mp3","ref":[12,806225,812494]},{"name":"12.5% C6F#.mp3","ref":[12,812494,818763]},{"name":"12.5% C6D.mp3","ref":[12,818763,825032]},{"name":"12.5% C6C#.mp3","ref":[12,825032,831301]},{"name":"12.5% C5G.mp3","ref":[12,831301,837570]},{"name":"12.5% C5F#.mp3","ref":[12,837570,843839]},{"name":"12.5% C5E.mp3","ref":[12,843839,850108]},{"name":"12.5% C5D.mp3","ref":[12,850108,856377]},{"name":"12.5% C5C.mp3","ref":[12,856377,862646]},{"name":"12.5% C5C#.mp3","ref":[12,862646,868915]},{"name":"12.5% C5B.mp3","ref":[12,868915,875184]},{"name":"12.5% C5A.mp3","ref":[12,875184,881453]},{"name":"12.5% C5A#.mp3","ref":[12,881453,887722]},{"name":"12.5% C4G.mp3","ref":[12,887722,893991]},{"name":"12.5% C4F#.mp3","ref":[12,893991,900260]},{"name":"12.5% C4E.mp3","ref":[12,900260,906529]},{"name":"12.5% C4D.mp3","ref":[12,906529,912798]},{"name":"12.5% C4C.mp3","ref":[12,912798,919067]},{"name":"12.5% C4C#.mp3","ref":[12,919067,925336]},{"name":"12.5% C4B.mp3","ref":[12,925336,931605]},{"name":"12.5% C4A.mp3","ref":[12,931605,937874]},{"name":"12.5% C4A#.mp3","ref":[12,937874,944143]},{"name":"25% 40-11.mp3","ref":[12,944143,950412]},{"name":"12.5% C3F#.mp3","ref":[12,950412,956681]},{"name":"12.5% C3E.mp3","ref":[12,956681,962950]},{"name":"12.5% C3B.mp3","ref":[12,962950,969219]},{"name":"12.5% C3A.mp3","ref":[12,969219,975488]},{"name":"12.5% C3A#.mp3","ref":[12,975488,981757]},{"name":"12.5% C2B.mp3","ref":[12,981757,988026]},{"name":"25% 40-14.mp3","ref":[12,988026,994295]},{"name":"25% 40-10.mp3","ref":[12,994295,1000564]},{"name":"ｱｺｰﾃﾞｨｵﾝ 51-1.mp3","ref":[12,1000564,1006833]},{"name":"25% 40-20.mp3","ref":[12,1006833,1013102]},{"name":"25% 39-9.mp3","ref":[12,1013102,1018953]},{"name":"25% 39-1.mp3","ref":[12,1018953,1024804]},{"name":"25% 39-2.mp3","ref":[12,1024804,1030655]},{"name":"25% 39-3.mp3","ref":[12,1030655,1036506]},{"name":"25% 39-4.mp3","ref":[12,1036506,1042357]},{"name":"25% 39-5.mp3","ref":[12,1042357,1048208]},{"name":"25% 39-6.mp3","ref":[12,1048208,1054059]},{"name":"25% 39-7.mp3","ref":[12,1054059,1059910]},{"name":"25% 39-8.mp3","ref":[12,1059910,1065761]},{"name":"25% 39-10.mp3","ref":[12,1065761,1071612]},{"name":"ｼﾝｾﾄﾞﾗﾑ ｺ3.mp3","ref":[12,1071612,1077463]},{"name":"ｼﾝｾﾄﾞﾗﾑ ｺ1.mp3","ref":[12,1077463,1083314]},{"name":"ｼﾝｾﾄﾞﾗﾑ ﾎﾟ6.mp3","ref":[12,1083314,1089165]},{"name":"ｼﾝｾﾄﾞﾗﾑ ﾎﾟ5.mp3","ref":[12,1089165,1095016]},{"name":"ｼﾝｾﾄﾞﾗﾑ ﾎﾟ4.mp3","ref":[12,1095016,1100867]},{"name":"ｼﾝｾﾄﾞﾗﾑ ﾎﾟ3.mp3","ref":[12,1100867,1106718]},{"name":"ｼﾝｾﾄﾞﾗﾑ ﾎﾟ2.mp3","ref":[12,1106718,1112569]},{"name":"ｼﾝｾﾄﾞﾗﾑ ﾎﾟ1.mp3","ref":[12,1112569,1118420]},{"name":"ｼﾝｾﾄﾞﾗﾑ ｺ2.mp3","ref":[12,1118420,1124271]},{"name":"僕たちの旅とエピローグ。.webm","ref":[13,0,12432054]},{"name":"ﾊﾞｯｸの音 69~.ogg","ref":[14,0,574707]},{"name":"ﾊﾞｯｸの音 3~.ogg","ref":[14,574707,1118596]},{"name":"ﾊﾞｯｸの音 33~.ogg","ref":[14,1118596,1424047]},{"name":"square 92-1.ogg","ref":[15,0,51261]},{"name":"square 9-1.ogg","ref":[15,51261,100558]},{"name":"ﾋﾟｱﾉ 4-6-1.ogg","ref":[15,100558,146067]},{"name":"ﾋﾟｱﾉ 4-1.ogg","ref":[15,146067,191343]},{"name":"ﾋﾟｱﾉ 4-10-1.ogg","ref":[15,191343,236586]},{"name":"ﾋﾟｱﾉ 4-7.ogg","ref":[15,236586,281022]},{"name":"ﾋﾟｱﾉ 4-8-2.ogg","ref":[15,281022,325430]},{"name":"ﾋﾟｱﾉ 4-6-2.ogg","ref":[15,325430,369676]},{"name":"ﾋﾟｱﾉ 4-5-2.ogg","ref":[15,369676,413632]},{"name":"ﾋﾟｱﾉ 4-2.ogg","ref":[15,413632,457384]},{"name":"ﾋﾟｱﾉ 4-11.ogg","ref":[15,457384,500724]},{"name":"ﾋﾟｱﾉ 4-10-2.ogg","ref":[15,500724,543983]},{"name":"ﾋﾟｱﾉ 4-9.ogg","ref":[15,543983,586731]},{"name":"ﾋﾟｱﾉ 4-3-2.ogg","ref":[15,586731,628992]},{"name":"ﾋﾟｱﾉ 4-3-1.ogg","ref":[15,628992,670619]},{"name":"ﾋﾟｱﾉ 4-8-1.ogg","ref":[15,670619,711597]},{"name":"ﾋﾟｱﾉ 4-4.ogg","ref":[15,711597,751690]},{"name":"25% 99-1-1.ogg","ref":[15,751690,790538]},{"name":"ﾋﾟｱﾉ 4-5-1.ogg","ref":[15,790538,829030]},{"name":"12.5% 15-2.ogg","ref":[15,829030,866924]},{"name":"ﾄﾞﾗﾑ C2A symbal.ogg","ref":[15,866924,904643]},{"name":"ﾄﾞﾗﾑ C2E symbal.ogg","ref":[15,904643,941459]},{"name":"ﾄﾗﾝﾍﾟｯﾄ　52-2.ogg","ref":[15,941459,976837]},{"name":"ﾄﾗﾝﾍﾟｯﾄ　50-1-2.ogg","ref":[15,976837,1011243]},{"name":"ﾄﾞﾗﾑ 8 snare roll.ogg","ref":[15,1011243,1045512]},{"name":"ﾄﾗﾝﾍﾟｯﾄ　49-1.ogg","ref":[15,1045512,1079633]},{"name":"12.5% 73-1.ogg","ref":[15,1079633,1111978]},{"name":"ﾄﾗﾝﾍﾟｯﾄ　52-1-2.ogg","ref":[15,1111978,1143756]},{"name":"ｼﾝｾﾄﾞﾗﾑ symbal+ｼｬﾗｰﾝ.ogg","ref":[15,1143756,1174840]},{"name":"triangle 99-1-3.ogg","ref":[15,1174840,1205539]},{"name":"ﾄﾗﾝﾍﾟｯﾄ　50-1-1.ogg","ref":[15,1205539,1236053]},{"name":"square 40-1-1.ogg","ref":[15,1236053,1266309]},{"name":"square 8-2.ogg","ref":[15,1266309,1296542]},{"name":"ﾄﾗﾝﾍﾟｯﾄ　51-1-1.ogg","ref":[15,1296542,1326572]},{"name":"ﾋﾟｱﾉ 41-1.ogg","ref":[15,1326572,1356546]},{"name":"square 8-1.ogg","ref":[15,1356546,1386412]},{"name":"ﾄﾗﾝﾍﾟｯﾄ　51-1-2.ogg","ref":[15,1386412,1416236]},{"name":"ﾄﾗﾝﾍﾟｯﾄ　51-2-2.ogg","ref":[15,1416236,1446031]},{"name":"square 40-1-2.ogg","ref":[16,0,29684]},{"name":"ﾄﾗﾝﾍﾟｯﾄ　51-2-1.ogg","ref":[16,29684,59041]},{"name":"25% 66-1-1.ogg","ref":[16,59041,88346]},{"name":"triangle 99-1-1.ogg","ref":[16,88346,117640]},{"name":"square 7-3.ogg","ref":[16,117640,146238]},{"name":"ﾄﾗﾝﾍﾟｯﾄ　52-1-1.ogg","ref":[16,146238,174804]},{"name":"25% 100-1.ogg","ref":[16,174804,202809]},{"name":"ﾄﾗﾝﾍﾟｯﾄ　51_-3.ogg","ref":[16,202809,230607]},{"name":"口笛　56-1.ogg","ref":[16,230607,257905]},{"name":"ﾄﾗﾝﾍﾟｯﾄ　50-4.ogg","ref":[16,257905,285134]},{"name":"ﾄﾗﾝﾍﾟｯﾄ　6-3-2.ogg","ref":[16,285134,312357]},{"name":"ｶﾘｵﾍﾟ　47-2.ogg","ref":[16,312357,339576]},{"name":"triangle 39-1.ogg","ref":[16,339576,366575]},{"name":"ﾋﾟｱﾉ 41-7-1.ogg","ref":[16,366575,393437]},{"name":"25% 66-1-2.ogg","ref":[16,393437,419963]},{"name":"ﾄﾗﾝﾍﾟｯﾄ　51_-1.ogg","ref":[16,419963,446374]},{"name":"ﾄﾗﾝﾍﾟｯﾄ　50-3.ogg","ref":[16,446374,472746]},{"name":"ﾄﾗﾝﾍﾟｯﾄ　50-2.ogg","ref":[16,472746,498997]},{"name":"ﾋﾟｱﾉ 42-1.ogg","ref":[16,498997,524936]},{"name":"ﾄﾗﾝﾍﾟｯﾄ　50_-2.ogg","ref":[16,524936,550679]},{"name":"ﾄﾗﾝﾍﾟｯﾄ　52_-3.ogg","ref":[16,550679,576039]},{"name":"ﾄﾗﾝﾍﾟｯﾄ　6-3-1.ogg","ref":[16,576039,601218]},{"name":"ﾄﾗﾝﾍﾟｯﾄ　52_-1.ogg","ref":[16,601218,626352]},{"name":"25% 67-1-2.ogg","ref":[16,626352,651482]},{"name":"square 85-3.ogg","ref":[16,651482,676506]},{"name":"ﾋﾟｱﾉ 43-1.ogg","ref":[16,676506,701478]},{"name":"12.5% 13-1.ogg","ref":[16,701478,725973]},{"name":"ﾋﾟｱﾉ 45-1-2.ogg","ref":[16,725973,750330]},{"name":"ﾄﾗﾝﾍﾟｯﾄ　89-2-2.ogg","ref":[16,750330,774523]},{"name":"ﾋﾟｱﾉ 44-1.ogg","ref":[16,774523,798598]},{"name":"square 75-2.ogg","ref":[16,798598,822558]},{"name":"square 77-1.ogg","ref":[16,822558,846508]},{"name":"ﾋﾟｱﾉ 46-1-1.ogg","ref":[16,846508,870407]},{"name":"25% 56-1-2.ogg","ref":[16,870407,894304]},{"name":"ﾋﾟｱﾉ 46-1-2.ogg","ref":[16,894304,918048]},{"name":"square 76-1.ogg","ref":[16,918048,941740]},{"name":"square 85-1.ogg","ref":[16,941740,965416]},{"name":"square 79-1.ogg","ref":[16,965416,989078]},{"name":"square 78-4.ogg","ref":[16,989078,1012732]},{"name":"square 81-6.ogg","ref":[16,1012732,1036286]},{"name":"ﾄﾗﾝﾍﾟｯﾄ　88-2-2.ogg","ref":[16,1036286,1059822]},{"name":"square 84-4.ogg","ref":[16,1059822,1083339]},{"name":"square 84-1.ogg","ref":[16,1083339,1106836]},{"name":"square 79-5.ogg","ref":[16,1106836,1130325]},{"name":"25% 67-1-1.ogg","ref":[16,1130325,1153654]},{"name":"square 74-4.ogg","ref":[16,1153654,1176948]},{"name":"25% 53-1-2.ogg","ref":[16,1176948,1200148]},{"name":"square 77-3.ogg","ref":[16,1200148,1223339]},{"name":"25% 53-1-1.ogg","ref":[16,1223339,1246518]},{"name":"square 75-3.ogg","ref":[16,1246518,1269696]},{"name":"square 76-3.ogg","ref":[16,1269696,1292864]},{"name":"ﾋﾟｱﾉ 45-1-1.ogg","ref":[16,1292864,1315989]},{"name":"square 91-2.ogg","ref":[16,1315989,1339089]},{"name":"25% 56-1-1.ogg","ref":[16,1339089,1362174]},{"name":"square 86-4.ogg","ref":[16,1362174,1385238]},{"name":"square 79-2.ogg","ref":[16,1385238,1408286]},{"name":"square 82-1.ogg","ref":[16,1408286,1431262]},{"name":"ﾋﾟｱﾉ 41-2.ogg","ref":[16,1431262,1454207]},{"name":"square 89-3.ogg","ref":[17,0,22937]},{"name":"square 81-1.ogg","ref":[17,22937,45859]},{"name":"square 78-6.ogg","ref":[17,45859,68769]},{"name":"square 81-4.ogg","ref":[17,68769,91678]},{"name":"square 88-4.ogg","ref":[17,91678,114524]},{"name":"square 89-4.ogg","ref":[17,114524,137370]},{"name":"square 87-5.ogg","ref":[17,137370,160216]},{"name":"ﾋﾟｱﾉ 43-2.ogg","ref":[17,160216,183055]},{"name":"25% 54-1-2.ogg","ref":[17,183055,205893]},{"name":"25% 55-1-2.ogg","ref":[17,205893,228729]},{"name":"square 76-4.ogg","ref":[17,228729,251560]},{"name":"square 76-2.ogg","ref":[17,251560,274376]},{"name":"square 91-1.ogg","ref":[17,274376,297168]},{"name":"ﾄﾗﾝﾍﾟｯﾄ　51_-4.ogg","ref":[17,297168,319913]},{"name":"square 85-4.ogg","ref":[17,319913,342651]},{"name":"square 87-1.ogg","ref":[17,342651,365386]},{"name":"square 74-1.ogg","ref":[17,365386,388112]},{"name":"25% 55-1-1.ogg","ref":[17,388112,410823]},{"name":"ﾄﾞﾗﾑ C2C# symbal.ogg","ref":[17,410823,433521]},{"name":"square 80-4.ogg","ref":[17,433521,456213]},{"name":"square 74-6.ogg","ref":[17,456213,478882]},{"name":"square 77-4.ogg","ref":[17,478882,501548]},{"name":"square 74-2.ogg","ref":[17,501548,524166]},{"name":"ﾄﾗﾝﾍﾟｯﾄ　51_-2.ogg","ref":[17,524166,546742]},{"name":"ﾄﾗﾝﾍﾟｯﾄ　5-3-2.ogg","ref":[17,546742,569246]},{"name":"25% 66-1-3.ogg","ref":[17,569246,591730]},{"name":"square 86-2.ogg","ref":[17,591730,614198]},{"name":"ﾋﾟｱﾉ 42-2.ogg","ref":[17,614198,636656]},{"name":"square 80-3.ogg","ref":[17,636656,659087]},{"name":"square 87-2.ogg","ref":[17,659087,681508]},{"name":"square 83-2.ogg","ref":[17,681508,703921]},{"name":"square 80-1.ogg","ref":[17,703921,726330]},{"name":"square 82-2.ogg","ref":[17,726330,748712]},{"name":"square 74-7.ogg","ref":[17,748712,771072]},{"name":"square 84-6.ogg","ref":[17,771072,793402]},{"name":"square 83-3.ogg","ref":[17,793402,815708]},{"name":"square 83-1.ogg","ref":[17,815708,838014]},{"name":"square 86-6.ogg","ref":[17,838014,860320]},{"name":"square 88-1.ogg","ref":[17,860320,882614]},{"name":"square 75-4.ogg","ref":[17,882614,904908]},{"name":"ﾋﾟｱﾉ 43-8.ogg","ref":[17,904908,927198]},{"name":"square 78-1.ogg","ref":[17,927198,949475]},{"name":"square 90-4.ogg","ref":[17,949475,971751]},{"name":"square 80-5.ogg","ref":[17,971751,993972]},{"name":"square 84-5.ogg","ref":[17,993972,1016177]},{"name":"square 83-4.ogg","ref":[17,1016177,1038382]},{"name":"ﾋﾟｱﾉ 44-2.ogg","ref":[17,1038382,1060583]},{"name":"square 85-2.ogg","ref":[17,1060583,1082781]},{"name":"square 82-7.ogg","ref":[17,1082781,1104974]},{"name":"ﾄﾗﾝﾍﾟｯﾄ　5-3-1.ogg","ref":[17,1104974,1127167]},{"name":"square 87-3.ogg","ref":[17,1127167,1149358]},{"name":"square 74-5.ogg","ref":[17,1149358,1171541]},{"name":"square 88-3.ogg","ref":[17,1171541,1193663]},{"name":"square 86-1.ogg","ref":[17,1193663,1215785]},{"name":"triangle 88-1.ogg","ref":[17,1215785,1237902]},{"name":"square 84-7.ogg","ref":[17,1237902,1259990]},{"name":"square 81-3.ogg","ref":[17,1259990,1282070]},{"name":"square 77-2.ogg","ref":[17,1282070,1304125]},{"name":"ﾄﾗﾝﾍﾟｯﾄ　88-2-1.ogg","ref":[17,1304125,1326163]},{"name":"square 57-7.ogg","ref":[17,1326163,1348193]},{"name":"ﾄﾗﾝﾍﾟｯﾄ　49_-2.ogg","ref":[17,1348193,1370215]},{"name":"25% 67-2.ogg","ref":[17,1370215,1392229]},{"name":"square 78-5.ogg","ref":[17,1392229,1414210]},{"name":"square 80-2.ogg","ref":[17,1414210,1436167]},{"name":"square 79-3.ogg","ref":[17,1436167,1458119]},{"name":"square 87-4.ogg","ref":[18,0,21942]},{"name":"square 81-2.ogg","ref":[18,21942,43876]},{"name":"square 82-8.ogg","ref":[18,43876,65756]},{"name":"square 84-2.ogg","ref":[18,65756,87607]},{"name":"square 75-1.ogg","ref":[18,87607,109452]},{"name":"square 90-3.ogg","ref":[18,109452,131281]},{"name":"square 82-6.ogg","ref":[18,131281,153014]},{"name":"square 76-5.ogg","ref":[18,153014,174733]},{"name":"square 84-3.ogg","ref":[18,174733,196449]},{"name":"square 89-1.ogg","ref":[18,196449,218165]},{"name":"square 82-4.ogg","ref":[18,218165,239771]},{"name":"square 57-4.ogg","ref":[18,239771,261347]},{"name":"square 57-2.ogg","ref":[18,261347,282923]},{"name":"square 78-2.ogg","ref":[18,282923,304492]},{"name":"square 57-6.ogg","ref":[18,304492,326049]},{"name":"ﾋﾟｱﾉ 41-3.ogg","ref":[18,326049,347579]},{"name":"square 90-5.ogg","ref":[18,347579,369109]},{"name":"square 82-5.ogg","ref":[18,369109,390632]},{"name":"square 57-5.ogg","ref":[18,390632,412139]},{"name":"square 57-1.ogg","ref":[18,412139,433646]},{"name":"triangle 35-code.ogg","ref":[18,433646,455107]},{"name":"triangle 30-code.ogg","ref":[18,455107,476552]},{"name":"ﾋﾟｱﾉ 3-11.ogg","ref":[18,476552,497995]},{"name":"square 86-5.ogg","ref":[18,497995,519340]},{"name":"square 86-3.ogg","ref":[18,519340,540685]},{"name":"square 88-2.ogg","ref":[18,540685,562030]},{"name":"ﾋﾟｱﾉ 42-3.ogg","ref":[18,562030,583368]},{"name":"triangle 36-code.ogg","ref":[18,583368,604705]},{"name":"triangle 32-code.ogg","ref":[18,604705,626042]},{"name":"square 1-1.ogg","ref":[18,626042,647367]},{"name":"square 82-3.ogg","ref":[18,647367,668672]},{"name":"triangle 25-code.ogg","ref":[18,668672,689966]},{"name":"ﾋﾟｱﾉ 3-5.ogg","ref":[18,689966,711257]},{"name":"square 89-2.ogg","ref":[18,711257,732534]},{"name":"ﾋﾟｱﾉ 3-6.ogg","ref":[18,732534,753809]},{"name":"triangle 34-code.ogg","ref":[18,753809,775072]},{"name":"25% 65-1-3.ogg","ref":[18,775072,796321]},{"name":"ﾋﾟｱﾉ 43-3.ogg","ref":[18,796321,817566]},{"name":"square 90-1.ogg","ref":[18,817566,838772]},{"name":"square 78-3.ogg","ref":[18,838772,859953]},{"name":"square 2-3.ogg","ref":[18,859953,881119]},{"name":"triangle 28-code.ogg","ref":[18,881119,902259]},{"name":"square 74-3.ogg","ref":[18,902259,923369]},{"name":"triangle 33-code.ogg","ref":[18,923369,944455]},{"name":"triangle 29-code.ogg","ref":[18,944455,965529]},{"name":"ﾄﾗﾝﾍﾟｯﾄ　6-1-2.ogg","ref":[18,965529,986600]},{"name":"square 39-4-2.ogg","ref":[18,986600,1007660]},{"name":"triangle 38-code.ogg","ref":[18,1007660,1028647]},{"name":"ﾋﾟｱﾉ 3-10.ogg","ref":[18,1028647,1049573]},{"name":"triangle 27-code.ogg","ref":[18,1049573,1070498]},{"name":"triangle 31-code.ogg","ref":[18,1070498,1091423]},{"name":"square 57-3.ogg","ref":[18,1091423,1112329]},{"name":"square 2-4.ogg","ref":[18,1112329,1133216]},{"name":"25% 64-1.ogg","ref":[18,1133216,1154097]},{"name":"ﾋﾟｱﾉ 3-12.ogg","ref":[18,1154097,1174916]},{"name":"triangle 37-code.ogg","ref":[18,1174916,1195674]},{"name":"ﾋﾟｱﾉ 3-4.ogg","ref":[18,1195674,1216417]},{"name":"ﾋﾟｱﾉ 3-8.ogg","ref":[18,1216417,1237135]},{"name":"ﾋﾟｱﾉ 3-2.ogg","ref":[18,1237135,1257846]},{"name":"square 82-9.ogg","ref":[18,1257846,1278543]},{"name":"triangle 26-code.ogg","ref":[18,1278543,1299232]},{"name":"square 81-5.ogg","ref":[18,1299232,1319906]},{"name":"ﾋﾟｱﾉ 44-3.ogg","ref":[18,1319906,1340540]},{"name":"ﾄﾗﾝﾍﾟｯﾄ　89-1-2.ogg","ref":[18,1340540,1361174]},{"name":"square 90-2.ogg","ref":[18,1361174,1381782]},{"name":"square 79-4.ogg","ref":[18,1381782,1402389]},{"name":"ﾋﾟｱﾉ 3-9.ogg","ref":[18,1402389,1422956]},{"name":"triangle 40-code.ogg","ref":[18,1422956,1443446]},{"name":"25% 99-1-2.ogg","ref":[18,1443446,1463928]},{"name":"ﾄﾗﾝﾍﾟｯﾄ　81-2-2.ogg","ref":[19,0,20465]},{"name":"ﾋﾟｱﾉ 3-3.ogg","ref":[19,20465,40857]},{"name":"ﾄﾞﾗﾑ C2G symbal.ogg","ref":[19,40857,61223]},{"name":"triangle 39-code.ogg","ref":[19,61223,81539]},{"name":"ﾄﾞﾗﾑ C2F symbal.ogg","ref":[19,81539,101787]},{"name":"square 4-1.ogg","ref":[19,101787,121842]},{"name":"ﾄﾗﾝﾍﾟｯﾄ　89-2-1.ogg","ref":[19,121842,141896]},{"name":"triangle 90-1.ogg","ref":[19,141896,161915]},{"name":"ﾋﾟｱﾉ 3-7.ogg","ref":[19,161915,181918]},{"name":"square 2-5.ogg","ref":[19,181918,201817]},{"name":"25% 98-1-1.ogg","ref":[19,201817,221637]},{"name":"ﾋﾟｱﾉ 3-1.ogg","ref":[19,221637,241365]},{"name":"25% 64-2.ogg","ref":[19,241365,260981]},{"name":"square 1-5.ogg","ref":[19,260981,280542]},{"name":"ｶﾘｵﾍﾟ　43-1.ogg","ref":[19,280542,299953]},{"name":"12.5% 70-3.ogg","ref":[19,299953,319364]},{"name":"ﾋﾟｱﾉ 41-4.ogg","ref":[19,319364,338771]},{"name":"triangle 99-1-2.ogg","ref":[19,338771,358114]},{"name":"ﾋﾟｱﾉ 44-4.ogg","ref":[19,358114,377450]},{"name":"ﾊｰﾌﾟ　C2D.ogg","ref":[19,377450,396753]},{"name":"ﾊｰﾌﾟ　C1A.ogg","ref":[19,396753,416047]},{"name":"square 1-7.ogg","ref":[19,416047,435298]},{"name":"口笛　55-2.ogg","ref":[19,435298,454471]},{"name":"square 1-6.ogg","ref":[19,454471,473636]},{"name":"ﾋﾟｱﾉ 1-5.ogg","ref":[19,473636,492701]},{"name":"ﾄﾗﾝﾍﾟｯﾄ　81-2-1.ogg","ref":[19,492701,511747]},{"name":"ﾋﾟｱﾉ 1-7-1.ogg","ref":[19,511747,530753]},{"name":"triangle 98-1-2.ogg","ref":[19,530753,549737]},{"name":"square 1-2.ogg","ref":[19,549737,568680]},{"name":"口笛　55-3.ogg","ref":[19,568680,587595]},{"name":"triangle 100-1.ogg","ref":[19,587595,606461]},{"name":"square 1-3.ogg","ref":[19,606461,625311]},{"name":"ﾊｰﾌﾟ　C4D.ogg","ref":[19,625311,644116]},{"name":"ﾋﾟｱﾉ 2-5.ogg","ref":[19,644116,662909]},{"name":"ﾋﾟｱﾉ 2-7-1.ogg","ref":[19,662909,681681]},{"name":"ﾄﾗﾝﾍﾟｯﾄ　89-1-1.ogg","ref":[19,681681,700435]},{"name":"ﾄﾗﾝﾍﾟｯﾄ　6-1-1.ogg","ref":[19,700435,719187]},{"name":"square 1-4.ogg","ref":[19,719187,737934]},{"name":"ﾋﾟｱﾉ 1-6.ogg","ref":[19,737934,756666]},{"name":"口笛　54-2.ogg","ref":[19,756666,775349]},{"name":"ﾋﾟｱﾉ 2-6-1.ogg","ref":[19,775349,794008]},{"name":"ﾋﾟｱﾉ 2-7-2.ogg","ref":[19,794008,812656]},{"name":"ﾊｰﾌﾟ　C4C#.ogg","ref":[19,812656,831274]},{"name":"ﾋﾟｱﾉ 1-4.ogg","ref":[19,831274,849884]},{"name":"ﾋﾟｱﾉ 2-3.ogg","ref":[19,849884,868490]},{"name":"ﾊｰﾌﾟ　C4G.ogg","ref":[19,868490,887074]},{"name":"square 3-2.ogg","ref":[19,887074,905650]},{"name":"ﾊｰﾌﾟ　C4E.ogg","ref":[19,905650,924220]},{"name":"ﾋﾟｱﾉ 2-4.ogg","ref":[19,924220,942757]},{"name":"ﾊｰﾌﾟ　C4A.ogg","ref":[19,942757,961289]},{"name":"ﾊｰﾌﾟ　C4F#.ogg","ref":[19,961289,979806]},{"name":"square 6-4.ogg","ref":[19,979806,998308]},{"name":"ﾊｰﾌﾟ　C3A#.ogg","ref":[19,998308,1016807]},{"name":"ﾊｰﾌﾟ　C4B.ogg","ref":[19,1016807,1035302]},{"name":"ﾊｰﾌﾟ　C5C#.ogg","ref":[19,1035302,1053777]},{"name":"ﾊｰﾌﾟ　C4A#.ogg","ref":[19,1053777,1072203]},{"name":"ﾋﾟｱﾉ 1-7-2.ogg","ref":[19,1072203,1090601]},{"name":"ﾋﾟｱﾉ 1-8-1.ogg","ref":[19,1090601,1108985]},{"name":"ﾋﾟｱﾉ 1-1.ogg","ref":[19,1108985,1127367]},{"name":"ﾋﾟｱﾉ 1-3.ogg","ref":[19,1127367,1145745]},{"name":"ﾊｰﾌﾟ　C3A.ogg","ref":[19,1145745,1164117]},{"name":"ﾋﾟｱﾉ 2-6-2.ogg","ref":[19,1164117,1182488]},{"name":"25% 98-1-2.ogg","ref":[19,1182488,1200854]},{"name":"ﾋﾟｱﾉ 41-5.ogg","ref":[19,1200854,1219194]},{"name":"ﾊｰﾌﾟ　C3B.ogg","ref":[19,1219194,1237501]},{"name":"ﾋﾟｱﾉ 2-2.ogg","ref":[19,1237501,1255805]},{"name":"square 3-5.ogg","ref":[19,1255805,1274099]},{"name":"ﾊｰﾌﾟ　C5D.ogg","ref":[19,1274099,1292370]},{"name":"口笛　55-5.ogg","ref":[19,1292370,1310626]},{"name":"square 2-2.ogg","ref":[19,1310626,1328849]},{"name":"square 39-1-2.ogg","ref":[19,1328849,1347058]},{"name":"ﾋﾟｱﾉ 1-8-2.ogg","ref":[19,1347058,1365264]},{"name":"ﾊｰﾌﾟ　C4C.ogg","ref":[19,1365264,1383453]},{"name":"ﾊｰﾌﾟ　C2A#.ogg","ref":[19,1383453,1401630]},{"name":"ﾋﾟｱﾉ 2-1.ogg","ref":[19,1401630,1419792]},{"name":"口笛　55-4.ogg","ref":[19,1419792,1437948]},{"name":"ﾊｰﾌﾟ　C3G.ogg","ref":[19,1437948,1456092]},{"name":"square 3-3.ogg","ref":[19,1456092,1474216]},{"name":"口笛　54-3.ogg","ref":[20,0,18093]},{"name":"ﾊｰﾌﾟ　C5G.ogg","ref":[20,18093,36182]},{"name":"ﾊｰﾌﾟ　C3F#.ogg","ref":[20,36182,54268]},{"name":"ﾊｰﾌﾟ　C2G.ogg","ref":[20,54268,72351]},{"name":"ﾊｰﾌﾟ　C5E.ogg","ref":[20,72351,90415]},{"name":"ﾋﾟｱﾉ 1-2.ogg","ref":[20,90415,108466]},{"name":"square 3-4.ogg","ref":[20,108466,126514]},{"name":"口笛　52-1.ogg","ref":[20,126514,144560]},{"name":"ﾊｰﾌﾟ　C3C#.ogg","ref":[20,144560,162595]},{"name":"ﾊｰﾌﾟ　C3E.ogg","ref":[20,162595,180630]},{"name":"口笛　53-2.ogg","ref":[20,180630,198566]},{"name":"ﾊｰﾌﾟ　C2F#.ogg","ref":[20,198566,216473]},{"name":"口笛　54-4.ogg","ref":[20,216473,234373]},{"name":"口笛　54-1.ogg","ref":[20,234373,252223]},{"name":"ﾊｰﾌﾟ　C2E.ogg","ref":[20,252223,270054]},{"name":"口笛　53-1.ogg","ref":[20,270054,287876]},{"name":"ﾊｰﾌﾟ　C2B.ogg","ref":[20,287876,305696]},{"name":"ﾊｰﾌﾟ　C5F#.ogg","ref":[20,305696,323511]},{"name":"square 6-5.ogg","ref":[20,323511,341326]},{"name":"口笛　53-3.ogg","ref":[20,341326,359132]},{"name":"square 39-1-1.ogg","ref":[20,359132,376903]},{"name":"ｶﾘｵﾍﾟ　47-1.ogg","ref":[20,376903,394576]},{"name":"ﾊｰﾌﾟ　C2A.ogg","ref":[20,394576,412249]},{"name":"square 5-4.ogg","ref":[20,412249,429867]},{"name":"ﾄﾗﾝﾍﾟｯﾄ　5-1-1.ogg","ref":[20,429867,447378]},{"name":"square 4-2.ogg","ref":[20,447378,464838]},{"name":"square 6-1.ogg","ref":[20,464838,482294]},{"name":"square 4-4.ogg","ref":[20,482294,499750]},{"name":"square 7-1.ogg","ref":[20,499750,517187]},{"name":"ｶﾘｵﾍﾟ　46-4.ogg","ref":[20,517187,534559]},{"name":"ｶﾘｵﾍﾟ　46-3.ogg","ref":[20,534559,551926]},{"name":"square 6-2.ogg","ref":[20,551926,569271]},{"name":"ﾊｰﾌﾟ　C5A.ogg","ref":[20,569271,586564]},{"name":"ﾋﾟｱﾉ 43-5-1.ogg","ref":[20,586564,603835]},{"name":"ﾄﾗﾝﾍﾟｯﾄ　5-5-2.ogg","ref":[20,603835,621098]},{"name":"ﾄﾗﾝﾍﾟｯﾄ　5-6-2.ogg","ref":[20,621098,638346]},{"name":"口笛　55-1.ogg","ref":[20,638346,655590]},{"name":"ﾄﾗﾝﾍﾟｯﾄ　5-7-2.ogg","ref":[20,655590,672830]},{"name":"25% 69-1-1.ogg","ref":[20,672830,690056]},{"name":"ﾄﾗﾝﾍﾟｯﾄ　5-2-1.ogg","ref":[20,690056,707235]},{"name":"square 6-3.ogg","ref":[20,707235,724402]},{"name":"ﾄﾗﾝﾍﾟｯﾄ　5-4.ogg","ref":[20,724402,741561]},{"name":"square 4-3.ogg","ref":[20,741561,758718]},{"name":"ﾊｰﾌﾟ　C6C#.ogg","ref":[20,758718,775841]},{"name":"ﾋﾟｱﾉ 43-5-2.ogg","ref":[20,775841,792953]},{"name":"ｶﾘｵﾍﾟ　46-1.ogg","ref":[20,792953,810025]},{"name":"ﾄﾗﾝﾍﾟｯﾄ　6-2-2.ogg","ref":[20,810025,827093]},{"name":"ﾋﾟｱﾉ 48-1-2.ogg","ref":[20,827093,844118]},{"name":"ｶﾘｵﾍﾟ　46-2.ogg","ref":[20,844118,861142]},{"name":"square 5-1.ogg","ref":[20,861142,878125]},{"name":"ｶﾘｵﾍﾟ　45-3.ogg","ref":[20,878125,895107]},{"name":"ｶﾘｵﾍﾟ　44-1.ogg","ref":[20,895107,912032]},{"name":"ﾄﾗﾝﾍﾟｯﾄ　5-6-1.ogg","ref":[20,912032,928937]},{"name":"ﾋﾟｱﾉ 47-2-2.ogg","ref":[20,928937,945729]},{"name":"25% 68-1-2.ogg","ref":[20,945729,962452]},{"name":"ｶﾘｵﾍﾟ　42-1.ogg","ref":[20,962452,979168]},{"name":"25% 69-1-2.ogg","ref":[20,979168,995849]},{"name":"ﾄﾞﾗﾑ 6 snare roll.ogg","ref":[20,995849,1012523]},{"name":"ｶﾘｵﾍﾟ　44-3.ogg","ref":[20,1012523,1029179]},{"name":"ﾋﾟｱﾉ 47-1-2.ogg","ref":[20,1029179,1045810]},{"name":"ｶﾘｵﾍﾟ　45-2.ogg","ref":[20,1045810,1062392]},{"name":"ｶﾘｵﾍﾟ　44-2.ogg","ref":[20,1062392,1078891]},{"name":"ｶﾘｵﾍﾟ　44-4.ogg","ref":[20,1078891,1095390]},{"name":"ﾋﾟｱﾉ 41-6.ogg","ref":[20,1095390,1111880]},{"name":"ｶﾘｵﾍﾟ　45-4.ogg","ref":[20,1111880,1128362]},{"name":"ﾄﾗﾝﾍﾟｯﾄ　5-1-2.ogg","ref":[20,1128362,1144842]},{"name":"ﾋﾟｱﾉ 48-2-2.ogg","ref":[20,1144842,1161272]},{"name":"ﾄﾗﾝﾍﾟｯﾄ　5-5-1.ogg","ref":[20,1161272,1177688]},{"name":"ﾊｰﾌﾟ　C6E.ogg","ref":[20,1177688,1193919]},{"name":"ﾄﾗﾝﾍﾟｯﾄ　5-7-1.ogg","ref":[20,1193919,1210094]},{"name":"ﾄﾗﾝﾍﾟｯﾄ　6-2-1.ogg","ref":[20,1210094,1226251]},{"name":"ﾄﾗﾝﾍﾟｯﾄ　5-2-2.ogg","ref":[20,1226251,1242327]},{"name":"ﾋﾟｱﾉ 47-2-1.ogg","ref":[20,1242327,1258373]},{"name":"ﾋﾟｱﾉ 47-1-1.ogg","ref":[20,1258373,1274419]},{"name":"ﾋﾟｱﾉ 48-2-1.ogg","ref":[20,1274419,1290458]},{"name":"ﾋﾟｱﾉ 48-1-1.ogg","ref":[20,1290458,1306433]},{"name":"ｶﾘｵﾍﾟ　43-4.ogg","ref":[20,1306433,1322313]},{"name":"12.5% 72-10.ogg","ref":[20,1322313,1338174]},{"name":"12.5% 72-1.ogg","ref":[20,1338174,1354035]},{"name":"ﾊｰﾌﾟ　C7C#.ogg","ref":[20,1354035,1369742]},{"name":"ｶﾘｵﾍﾟ　43-3.ogg","ref":[20,1369742,1385401]},{"name":"triangle 27-2.ogg","ref":[20,1385401,1401036]},{"name":"12.5% 23-2.ogg","ref":[20,1401036,1416590]},{"name":"ﾋﾟｱﾉ 46-2.ogg","ref":[20,1416590,1432119]},{"name":"ﾊｰﾌﾟ　C6A.ogg","ref":[20,1432119,1447645]},{"name":"ﾊｰﾌﾟ　C7E.ogg","ref":[20,1447645,1463066]},{"name":"ﾄﾗﾝﾍﾟｯﾄ　52_-2.ogg","ref":[21,0,15283]},{"name":"25% 68-1-3.ogg","ref":[21,15283,30528]},{"name":"ﾄﾗﾝﾍﾟｯﾄ　50_-1.ogg","ref":[21,30528,45615]},{"name":"square 5-6.ogg","ref":[21,45615,60696]},{"name":"square 5-2.ogg","ref":[21,60696,75722]},{"name":"square 5-3.ogg","ref":[21,75722,90718]},{"name":"square 5-5.ogg","ref":[21,90718,105714]},{"name":"25% 65-2.ogg","ref":[21,105714,120701]},{"name":"square 3-6.ogg","ref":[21,120701,135678]},{"name":"ﾄﾗﾝﾍﾟｯﾄ　81-1-1.ogg","ref":[21,135678,150641]},{"name":"ﾋﾟｱﾉ 44-5.ogg","ref":[21,150641,165584]},{"name":"square 3-1.ogg","ref":[21,165584,180422]},{"name":"25% 69-1-3.ogg","ref":[21,180422,195204]},{"name":"square 39-5.ogg","ref":[21,195204,209837]},{"name":"ﾄﾗﾝﾍﾟｯﾄ　88-1-1.ogg","ref":[21,209837,224439]},{"name":"ｶﾘｵﾍﾟ　43-2.ogg","ref":[21,224439,239021]},{"name":"25% 68-2.ogg","ref":[21,239021,253574]},{"name":"ﾄﾗﾝﾍﾟｯﾄ　50_-3.ogg","ref":[21,253574,268067]},{"name":"ﾊｰﾌﾟ　C7A.ogg","ref":[21,268067,282545]},{"name":"ﾄﾗﾝﾍﾟｯﾄ　81-1-2.ogg","ref":[21,282545,296981]},{"name":"ｶﾘｵﾍﾟ　42-3.ogg","ref":[21,296981,311254]},{"name":"square 39-6.ogg","ref":[21,311254,325431]},{"name":"25% 54-2.ogg","ref":[21,325431,339591]},{"name":"square 7-2.ogg","ref":[21,339591,353720]},{"name":"ﾋﾟｱﾉ 44-9.ogg","ref":[21,353720,367790]},{"name":"ｶﾘｵﾍﾟ　42-4.ogg","ref":[21,367790,381832]},{"name":"ｱｺｰﾃﾞｨｵﾝ 52-1.ogg","ref":[21,381832,395863]},{"name":"triangle 37-3.ogg","ref":[21,395863,409699]},{"name":"ﾄﾗﾝﾍﾟｯﾄ　88-1-2.ogg","ref":[21,409699,423531]},{"name":"25% 54-1-1.ogg","ref":[21,423531,437338]},{"name":"ﾋﾟｱﾉ 44-8.ogg","ref":[21,437338,451039]},{"name":"square 39-4-1.ogg","ref":[21,451039,464636]},{"name":"12.5% 64-1.ogg","ref":[21,464636,478219]},{"name":"ﾄﾗﾝﾍﾟｯﾄ　49_-1.ogg","ref":[21,478219,491753]},{"name":"12.5% 60-3.ogg","ref":[21,491753,505277]},{"name":"triangle 33-4.ogg","ref":[21,505277,518775]},{"name":"ﾋﾟｱﾉ 44-7.ogg","ref":[21,518775,532199]},{"name":"triangle 83-1.ogg","ref":[21,532199,545567]},{"name":"triangle 83-2.ogg","ref":[21,545567,558915]},{"name":"12.5% 71-1.ogg","ref":[21,558915,572217]},{"name":"ｶﾘｵﾍﾟ　41-2.ogg","ref":[21,572217,585503]},{"name":"triangle 84-2.ogg","ref":[21,585503,598695]},{"name":"square 3-8.ogg","ref":[21,598695,611788]},{"name":"triangle 98-1-1.ogg","ref":[21,611788,624857]},{"name":"ｶﾘｵﾍﾟ　41-3.ogg","ref":[21,624857,637915]},{"name":"square 3-7.ogg","ref":[21,637915,650964]},{"name":"ｶﾘｵﾍﾟ　41-1.ogg","ref":[21,650964,663955]},{"name":"square 2-1.ogg","ref":[21,663955,676946]},{"name":"ﾛｯｸｵﾙｶﾞﾝ 47-6.ogg","ref":[21,676946,689859]},{"name":"ﾋﾟｱﾉ 42-10.ogg","ref":[21,689859,702628]},{"name":"ﾋﾟｱﾉ 41-8.ogg","ref":[21,702628,715314]},{"name":"12.5% 62-2.ogg","ref":[21,715314,727620]},{"name":"25% 58-1.ogg","ref":[21,727620,739873]},{"name":"ﾛｯｸｵﾙｶﾞﾝ 48-14.ogg","ref":[21,739873,751750]},{"name":"ﾄﾞﾗﾑ snare 125%.ogg","ref":[21,751750,763590]},{"name":"ﾛｯｸｵﾙｶﾞﾝ 48-13.ogg","ref":[21,763590,775389]},{"name":"ﾄﾞﾗﾑ snare 105%.ogg","ref":[21,775389,787145]},{"name":"ﾛｯｸｵﾙｶﾞﾝ 48-11.ogg","ref":[21,787145,798897]},{"name":"ﾛｯｸｵﾙｶﾞﾝ 48-3.ogg","ref":[21,798897,810643]},{"name":"ﾛｯｸｵﾙｶﾞﾝ 48-2.ogg","ref":[21,810643,822355]},{"name":"ﾛｯｸｵﾙｶﾞﾝ 48-12.ogg","ref":[21,822355,834060]},{"name":"ﾋﾟｱﾉ 44-6.ogg","ref":[21,834060,845733]},{"name":"ﾄﾞﾗﾑ snare 90%.ogg","ref":[21,845733,857401]},{"name":"ﾛｯｸｵﾙｶﾞﾝ 48-10.ogg","ref":[21,857401,869061]},{"name":"ｼﾝｾﾄﾞﾗﾑ symbal2.ogg","ref":[21,869061,880719]},{"name":"ｼﾝｾﾄﾞﾗﾑ symbal.ogg","ref":[21,880719,892377]},{"name":"square 39-2.ogg","ref":[21,892377,903973]},{"name":"ﾛｯｸｵﾙｶﾞﾝ 48-1.ogg","ref":[21,903973,915532]},{"name":"ﾛｯｸｵﾙｶﾞﾝ 48-5.ogg","ref":[21,915532,927057]},{"name":"25% 58-2-2.ogg","ref":[21,927057,938576]},{"name":"square 37-1.ogg","ref":[21,938576,950092]},{"name":"ﾛｯｸｵﾙｶﾞﾝ 48-9.ogg","ref":[21,950092,961594]},{"name":"square 37-5.ogg","ref":[21,961594,973040]},{"name":"ﾄﾞﾗﾑ snare 75%.ogg","ref":[21,973040,984442]},{"name":"square 37-4.ogg","ref":[21,984442,995835]},{"name":"square 38-1.ogg","ref":[21,995835,1007223]},{"name":"square 39-3.ogg","ref":[21,1007223,1018599]},{"name":"square 37-2.ogg","ref":[21,1018599,1029949]},{"name":"square 37-6.ogg","ref":[21,1029949,1041299]},{"name":"square 38-6.ogg","ref":[21,1041299,1052645]},{"name":"25% 58-2-1.ogg","ref":[21,1052645,1063978]},{"name":"ﾛｯｸｵﾙｶﾞﾝ 48-8.ogg","ref":[21,1063978,1075299]},{"name":"ﾃｨﾝﾊﾟﾆ C1A#.ogg","ref":[21,1075299,1086582]},{"name":"ﾛｯｸｵﾙｶﾞﾝ 48-4.ogg","ref":[21,1086582,1097847]},{"name":"ﾃｨﾝﾊﾟﾆ C1B.ogg","ref":[21,1097847,1109092]},{"name":"ﾛｯｸｵﾙｶﾞﾝ 48-6.ogg","ref":[21,1109092,1120330]},{"name":"ﾛｯｸｵﾙｶﾞﾝ 48-7.ogg","ref":[21,1120330,1131559]},{"name":"ﾃｨﾝﾊﾟﾆ C1A.ogg","ref":[21,1131559,1142738]},{"name":"square 38-2.ogg","ref":[21,1142738,1153902]},{"name":"square 38-5.ogg","ref":[21,1153902,1165055]},{"name":"ﾃｨﾝﾊﾟﾆ C1G.ogg","ref":[21,1165055,1176174]},{"name":"square 37-7.ogg","ref":[21,1176174,1187280]},{"name":"ﾃｨﾝﾊﾟﾆ C1G#.ogg","ref":[21,1187280,1198366]},{"name":"ﾋﾟｱﾉ 42-4-2.ogg","ref":[21,1198366,1209420]},{"name":"square 38-7.ogg","ref":[21,1209420,1220461]},{"name":"ﾋﾟｱﾉ 41-9.ogg","ref":[21,1220461,1231479]},{"name":"ﾃｨﾝﾊﾟﾆ C1F#.ogg","ref":[21,1231479,1242493]},{"name":"ﾃｨﾝﾊﾟﾆ C1E.ogg","ref":[21,1242493,1253399]},{"name":"ﾃｨﾝﾊﾟﾆ C1D.ogg","ref":[21,1253399,1264239]},{"name":"ﾃｨﾝﾊﾟﾆ C1C#.ogg","ref":[21,1264239,1275017]},{"name":"ﾃｨﾝﾊﾟﾆ C0A.ogg","ref":[21,1275017,1285747]},{"name":"triangle 32-4.ogg","ref":[21,1285747,1296400]},{"name":"ﾛｯｸｵﾙｶﾞﾝ 47-4.ogg","ref":[21,1296400,1306884]},{"name":"ﾛｯｸｵﾙｶﾞﾝ 47-7.ogg","ref":[21,1306884,1317335]},{"name":"ﾛｯｸｵﾙｶﾞﾝ 47-2.ogg","ref":[21,1317335,1327733]},{"name":"ﾛｯｸｵﾙｶﾞﾝ 47-9.ogg","ref":[21,1327733,1338072]},{"name":"ﾛｯｸｵﾙｶﾞﾝ 47-1.ogg","ref":[21,1338072,1348410]},{"name":"ﾛｯｸｵﾙｶﾞﾝ 47-3.ogg","ref":[21,1348410,1358739]},{"name":"ﾋﾟｱﾉ 42-4-1.ogg","ref":[21,1358739,1369063]},{"name":"ﾋﾟｱﾉ 41-10.ogg","ref":[21,1369063,1379353]},{"name":"12.5% 69-2.ogg","ref":[21,1379353,1389637]},{"name":"ﾛｯｸｵﾙｶﾞﾝ 47-8.ogg","ref":[21,1389637,1399863]},{"name":"ﾋﾟｱﾉ 42-7-2.ogg","ref":[21,1399863,1410089]},{"name":"ﾛｯｸｵﾙｶﾞﾝ 47-5.ogg","ref":[21,1410089,1420281]},{"name":"ﾋﾟｱﾉ 42-7-1.ogg","ref":[21,1420281,1430433]},{"name":"ﾛｯｸｵﾙｶﾞﾝ 47-10.ogg","ref":[21,1430433,1440532]},{"name":"ｶﾘｵﾍﾟ　42-2.ogg","ref":[21,1440532,1450487]},{"name":"25% 72-3.ogg","ref":[21,1450487,1460397]},{"name":"25% 72-1.ogg","ref":[21,1460397,1470295]},{"name":"triangle 35-1.ogg","ref":[22,0,9861]},{"name":"triangle 27_-2.ogg","ref":[22,9861,19700]},{"name":"ｱｺｰﾃﾞｨｵﾝ 51-5.ogg","ref":[22,19700,29529]},{"name":"triangle 36-1.ogg","ref":[22,29529,39340]},{"name":"ｶﾘｵﾍﾟ　45-1.ogg","ref":[22,39340,49073]},{"name":"triangle 82-1.ogg","ref":[22,49073,58746]},{"name":"12.5% 63-2.ogg","ref":[22,58746,68381]},{"name":"ｱｺｰﾃﾞｨｵﾝ 51-3.ogg","ref":[22,68381,78005]},{"name":"12.5% 59-2.ogg","ref":[22,78005,87626]},{"name":"25% 72-2.ogg","ref":[22,87626,97245]},{"name":"ｱｺｰﾃﾞｨｵﾝ 50-1.ogg","ref":[22,97245,106820]},{"name":"ｱｺｰﾃﾞｨｵﾝ 50-3.ogg","ref":[22,106820,116395]},{"name":"triangle 86-2.ogg","ref":[22,116395,125933]},{"name":"12.5% 14-3.ogg","ref":[22,125933,135470]},{"name":"ｱｺｰﾃﾞｨｵﾝ 50-2.ogg","ref":[22,135470,145001]},{"name":"12.5% 14-4.ogg","ref":[22,145001,154489]},{"name":"ﾋﾟｱﾉ 42-5.ogg","ref":[22,154489,163970]},{"name":"triangle 32-1.ogg","ref":[22,163970,173444]},{"name":"triangle 86-1.ogg","ref":[22,173444,182906]},{"name":"ｱｺｰﾃﾞｨｵﾝ 51-4.ogg","ref":[22,182906,192366]},{"name":"triangle 85-2.ogg","ref":[22,192366,201815]},{"name":"12.5% 65-1.ogg","ref":[22,201815,211260]},{"name":"25% 9_-1-1.ogg","ref":[22,211260,220664]},{"name":"25% 64-3-1.ogg","ref":[22,220664,230065]},{"name":"12.5% 69-3.ogg","ref":[22,230065,239434]},{"name":"ﾋﾟｱﾉ 43-4-2.ogg","ref":[22,239434,248794]},{"name":"triangle 86-3.ogg","ref":[22,248794,258136]},{"name":"triangle 85-4.ogg","ref":[22,258136,267478]},{"name":"triangle 86-4.ogg","ref":[22,267478,276796]},{"name":"triangle 82-3.ogg","ref":[22,276796,286108]},{"name":"triangle 85-1.ogg","ref":[22,286108,295415]},{"name":"ﾋﾟｱﾉ 43-4-1.ogg","ref":[22,295415,304721]},{"name":"triangle 87-4.ogg","ref":[22,304721,314027]},{"name":"25% 65-3-1.ogg","ref":[22,314027,323326]},{"name":"12.5% 61-1.ogg","ref":[22,323326,332624]},{"name":"12.5% 68-3.ogg","ref":[22,332624,341922]},{"name":"triangle 82-2.ogg","ref":[22,341922,351199]},{"name":"triangle 87-2.ogg","ref":[22,351199,360476]},{"name":"triangle 89-2.ogg","ref":[22,360476,369745]},{"name":"25% 11_-1-1.ogg","ref":[22,369745,379012]},{"name":"12.5% 61-2.ogg","ref":[22,379012,388272]},{"name":"12.5% 68-1.ogg","ref":[22,388272,397531]},{"name":"12.5% 65-4.ogg","ref":[22,397531,406790]},{"name":"12.5% 67-1.ogg","ref":[22,406790,416044]},{"name":"12.5% 63-1.ogg","ref":[22,416044,425295]},{"name":"12.5% 72-2.ogg","ref":[22,425295,434546]},{"name":"25% 65-5-1.ogg","ref":[22,434546,443793]},{"name":"triangle 87-1.ogg","ref":[22,443793,453039]},{"name":"12.5% 58-1.ogg","ref":[22,453039,462284]},{"name":"25% 65-3-2.ogg","ref":[22,462284,471527]},{"name":"12.5% 59-1.ogg","ref":[22,471527,480767]},{"name":"12.5% 62-3.ogg","ref":[22,480767,490005]},{"name":"triangle 98-2.ogg","ref":[22,490005,499239]},{"name":"12.5% 59-3.ogg","ref":[22,499239,508472]},{"name":"25% 65-1-1.ogg","ref":[22,508472,517698]},{"name":"12.5% 66-1.ogg","ref":[22,517698,526908]},{"name":"triangle 85-3.ogg","ref":[22,526908,536092]},{"name":"triangle 84-1.ogg","ref":[22,536092,545268]},{"name":"triangle 87-3.ogg","ref":[22,545268,554422]},{"name":"12.5% 68-2.ogg","ref":[22,554422,563545]},{"name":"25% 61-1-1.ogg","ref":[22,563545,572664]},{"name":"25% 64-5-1.ogg","ref":[22,572664,581781]},{"name":"12.5% 70-1.ogg","ref":[22,581781,590895]},{"name":"25% 64-5-2.ogg","ref":[22,590895,600003]},{"name":"25% 13_-1-1.ogg","ref":[22,600003,609105]},{"name":"25% 65-1-2.ogg","ref":[22,609105,618174]},{"name":"triangle 89-3.ogg","ref":[22,618174,627236]},{"name":"triangle 89-1.ogg","ref":[22,627236,636297]},{"name":"25% 64-3-2.ogg","ref":[22,636297,645349]},{"name":"ﾋﾟｱﾉ 41-11.ogg","ref":[22,645349,654394]},{"name":"ﾋﾟｱﾉ 42-8.ogg","ref":[22,654394,663429]},{"name":"25% 65-5-2.ogg","ref":[22,663429,672463]},{"name":"25% 11_-1-2.ogg","ref":[22,672463,681479]},{"name":"ﾋﾟｱﾉ 41-7-2.ogg","ref":[22,681479,690487]},{"name":"25% 61-2-1.ogg","ref":[22,690487,699457]},{"name":"ﾋﾟｱﾉ 42-6.ogg","ref":[22,699457,708426]},{"name":"25% 9_-1-2.ogg","ref":[22,708426,717230]},{"name":"ﾋﾟｱﾉ 41-12.ogg","ref":[22,717230,726025]},{"name":"25% 13_-1-2.ogg","ref":[22,726025,734778]},{"name":"25% 61-2-2.ogg","ref":[22,734778,743525]},{"name":"ｱｺｰﾃﾞｨｵﾝ 51-2.ogg","ref":[22,743525,752023]},{"name":"triangle 30-6.ogg","ref":[22,752023,760520]},{"name":"12.5% 65-3.ogg","ref":[22,760520,768928]},{"name":"triangle 31-2.ogg","ref":[22,768928,777286]},{"name":"triangle 29-6.ogg","ref":[22,777286,785644]},{"name":"ﾋﾟｱﾉ 42-9.ogg","ref":[22,785644,793986]},{"name":"12.5% 14-2.ogg","ref":[22,793986,802324]},{"name":"ﾋﾟｱﾉ 44-18.ogg","ref":[22,802324,810566]},{"name":"ｱｺｰﾃﾞｨｵﾝ 50-4.ogg","ref":[22,810566,818787]},{"name":"25% 61-1-2.ogg","ref":[22,818787,826959]},{"name":"triangle 34-4.ogg","ref":[22,826959,835117]},{"name":"ｱｺｰﾃﾞｨｵﾝ 49-3.ogg","ref":[22,835117,843260]},{"name":"ｼﾝｾﾄﾞﾗﾑ ｺ1.ogg","ref":[22,843260,851398]},{"name":"triangle 28-4.ogg","ref":[22,851398,859527]},{"name":"12.5% 60-2.ogg","ref":[22,859527,867649]},{"name":"triangle 34-1.ogg","ref":[22,867649,875722]},{"name":"ﾋﾟｱﾉ 42-15.ogg","ref":[22,875722,883763]},{"name":"triangle 29-1.ogg","ref":[22,883763,891794]},{"name":"triangle 28-3.ogg","ref":[22,891794,899797]},{"name":"triangle 27_-1.ogg","ref":[22,899797,907799]},{"name":"ｱｺｰﾃﾞｨｵﾝ 49-2.ogg","ref":[22,907799,915762]},{"name":"25% 53-bass1.ogg","ref":[22,915762,923657]},{"name":"ﾋﾟｱﾉ 43-9.ogg","ref":[22,923657,931546]},{"name":"ﾋﾟｱﾉ 43-7.ogg","ref":[22,931546,939435]},{"name":"ｼﾝｾﾄﾞﾗﾑ ｺ2.ogg","ref":[22,939435,947295]},{"name":"ｱｺｰﾃﾞｨｵﾝ 49-1.ogg","ref":[22,947295,955154]},{"name":"ﾋﾟｱﾉ 43-10.ogg","ref":[22,955154,962983]},{"name":"ﾋﾟｱﾉ 43-6.ogg","ref":[22,962983,970812]},{"name":"25% 9__D.ogg","ref":[22,970812,978627]},{"name":"ﾋﾟｱﾉ 44-17.ogg","ref":[22,978627,986400]},{"name":"25% 59-1.ogg","ref":[22,986400,994144]},{"name":"ﾋﾟｱﾉ 44-16.ogg","ref":[22,994144,1001873]},{"name":"ﾋﾟｱﾉ 42-14.ogg","ref":[22,1001873,1009592]},{"name":"25% 55-bass1.ogg","ref":[22,1009592,1017254]},{"name":"25% 60-1.ogg","ref":[22,1017254,1024877]},{"name":"ﾋﾟｱﾉ 44-15.ogg","ref":[22,1024877,1032495]},{"name":"25% 62-1.ogg","ref":[22,1032495,1040088]},{"name":"25% 63-1.ogg","ref":[22,1040088,1047619]},{"name":"25% 54-bass1.ogg","ref":[22,1047619,1055141]},{"name":"ﾄﾞﾗﾑ bass other.ogg","ref":[22,1055141,1062521]},{"name":"ﾄﾞﾗﾑ bass first.ogg","ref":[22,1062521,1069888]},{"name":"triangle 34-3.ogg","ref":[22,1069888,1077250]},{"name":"triangle 26-6.ogg","ref":[22,1077250,1084555]},{"name":"ﾋﾟｱﾉ 44-14.ogg","ref":[22,1084555,1091836]},{"name":"ﾋﾟｱﾉ 42-13.ogg","ref":[22,1091836,1099107]},{"name":"triangle 38-2.ogg","ref":[22,1099107,1106361]},{"name":"triangle 38-3.ogg","ref":[22,1106361,1113581]},{"name":"ﾋﾟｱﾉ 44-11.ogg","ref":[22,1113581,1120798]},{"name":"ﾋﾟｱﾉ 42-11.ogg","ref":[22,1120798,1128005]},{"name":"triangle 28-2.ogg","ref":[22,1128005,1135163]},{"name":"25% 9_-2-1.ogg","ref":[22,1135163,1142301]},{"name":"triangle 37-1.ogg","ref":[22,1142301,1149433]},{"name":"triangle 36-3.ogg","ref":[22,1149433,1156565]},{"name":"ﾋﾟｱﾉ 44-10.ogg","ref":[22,1156565,1163676]},{"name":"triangle 33-2.ogg","ref":[22,1163676,1170786]},{"name":"12.5% 66-3.ogg","ref":[22,1170786,1177885]},{"name":"12.5% 67-2.ogg","ref":[22,1177885,1184984]},{"name":"12.5% 66-2.ogg","ref":[22,1184984,1192075]},{"name":"12.5% 58-3.ogg","ref":[22,1192075,1199160]},{"name":"12.5% 67-3.ogg","ref":[22,1199160,1206231]},{"name":"12.5% 63-3.ogg","ref":[22,1206231,1213298]},{"name":"12.5% 58-4.ogg","ref":[22,1213298,1220351]},{"name":"25% 11_-2-1.ogg","ref":[22,1220351,1227402]},{"name":"25% 4-6.ogg","ref":[22,1227402,1234451]},{"name":"triangle 35-4.ogg","ref":[22,1234451,1241498]},{"name":"ﾋﾟｱﾉ 44-13.ogg","ref":[22,1241498,1248542]},{"name":"12.5% 58-2.ogg","ref":[22,1248542,1255582]},{"name":"25% 11_-2-2.ogg","ref":[22,1255582,1262619]},{"name":"ﾋﾟｱﾉ 42-12.ogg","ref":[22,1262619,1269653]},{"name":"25% 65-6.ogg","ref":[22,1269653,1276684]},{"name":"25% 13_-2-1.ogg","ref":[22,1276684,1283711]},{"name":"triangle 36-2.ogg","ref":[22,1283711,1290726]},{"name":"25% 65-4.ogg","ref":[22,1290726,1297732]},{"name":"25% 64-4.ogg","ref":[22,1297732,1304723]},{"name":"ﾋﾟｱﾉ 44-12.ogg","ref":[22,1304723,1311691]},{"name":"25% 4-5.ogg","ref":[22,1311691,1318639]},{"name":"ｼﾝｾﾄﾞﾗﾑ ｺ3.ogg","ref":[22,1318639,1325569]},{"name":"25% 4-3.ogg","ref":[22,1325569,1332494]},{"name":"25% 9_-2-2.ogg","ref":[22,1332494,1339369]},{"name":"25% 4-4.ogg","ref":[22,1339369,1346225]},{"name":"25% 13_-2-2.ogg","ref":[22,1346225,1353039]},{"name":"12.5% C5A.ogg","ref":[22,1353039,1359846]},{"name":"triangle 30-3.ogg","ref":[22,1359846,1366453]},{"name":"triangle 30-2.ogg","ref":[22,1366453,1373060]},{"name":"triangle 26-3.ogg","ref":[22,1373060,1379653]},{"name":"ｼﾝｾﾄﾞﾗﾑ bass.ogg","ref":[22,1379653,1386220]},{"name":"ｼﾝｾﾄﾞﾗﾑ bass2.ogg","ref":[22,1386220,1392787]},{"name":"25% 9-2.ogg","ref":[22,1392787,1399350]},{"name":"ｼﾝｾﾄﾞﾗﾑ snare.ogg","ref":[22,1399350,1405899]},{"name":"ｼﾝｾﾄﾞﾗﾑ snare2.ogg","ref":[22,1405899,1412448]},{"name":"triangle 30-4.ogg","ref":[22,1412448,1418993]},{"name":"25% 14-1.ogg","ref":[22,1418993,1425527]},{"name":"25% 13-2.ogg","ref":[22,1425527,1432053]},{"name":"ｱｺｰﾃﾞｨｵﾝ 50-5.ogg","ref":[22,1432053,1438566]},{"name":"triangle 36-4.ogg","ref":[22,1438566,1445074]},{"name":"triangle 25-2.ogg","ref":[22,1445074,1451568]},{"name":"triangle 26-2.ogg","ref":[22,1451568,1458062]},{"name":"triangle 35-3.ogg","ref":[22,1458062,1464556]},{"name":"triangle 30-5.ogg","ref":[22,1464556,1471047]},{"name":"triangle 29-3.ogg","ref":[23,0,6491]},{"name":"triangle 33-3.ogg","ref":[23,6491,12961]},{"name":"triangle 31-3.ogg","ref":[23,12961,19413]},{"name":"triangle 25-5.ogg","ref":[23,19413,25851]},{"name":"triangle 25-4.ogg","ref":[23,25851,32289]},{"name":"triangle 35-2.ogg","ref":[23,32289,38727]},{"name":"25% 4-7.ogg","ref":[23,38727,45147]},{"name":"25% 4-10.ogg","ref":[23,45147,51565]},{"name":"triangle 38-1.ogg","ref":[23,51565,57962]},{"name":"triangle 92-2.ogg","ref":[23,57962,64351]},{"name":"triangle 93-1.ogg","ref":[23,64351,70732]},{"name":"noise long.ogg","ref":[23,70732,77096]},{"name":"triangle 31-4.ogg","ref":[23,77096,83451]},{"name":"triangle 25-3.ogg","ref":[23,83451,89791]},{"name":"triangle 26-1.ogg","ref":[23,89791,96131]},{"name":"triangle 92-3.ogg","ref":[23,96131,102460]},{"name":"triangle 25-1.ogg","ref":[23,102460,108785]},{"name":"12.5% 12-4.ogg","ref":[23,108785,115100]},{"name":"12.5% C5A#.ogg","ref":[23,115100,121412]},{"name":"triangle 29-4.ogg","ref":[23,121412,127704]},{"name":"triangle 37-2.ogg","ref":[23,127704,133996]},{"name":"25% 3-2.ogg","ref":[23,133996,140280]},{"name":"12.5% C5C.ogg","ref":[23,140280,146561]},{"name":"12.5% 14-1.ogg","ref":[23,146561,152825]},{"name":"12.5% 12-1.ogg","ref":[23,152825,159083]},{"name":"12.5% 12-2.ogg","ref":[23,159083,165325]},{"name":"ｱｺｰﾃﾞｨｵﾝ 51-1.ogg","ref":[23,165325,171557]},{"name":"25% 3-1.ogg","ref":[23,171557,177789]},{"name":"25% 39-2.ogg","ref":[23,177789,184004]},{"name":"12.5% 12-3.ogg","ref":[23,184004,190211]},{"name":"12.5% C2B.ogg","ref":[23,190211,196401]},{"name":"12.5% C5F#.ogg","ref":[23,196401,202549]},{"name":"12.5% C6F#.ogg","ref":[23,202549,208694]},{"name":"12.5% C5B.ogg","ref":[23,208694,214835]},{"name":"12.5% C5E.ogg","ref":[23,214835,220976]},{"name":"12.5% C3B.ogg","ref":[23,220976,227111]},{"name":"12.5% C4G.ogg","ref":[23,227111,233233]},{"name":"12.5% C3G.ogg","ref":[23,233233,239355]},{"name":"12.5% C4F#.ogg","ref":[23,239355,245474]},{"name":"12.5% C4B.ogg","ref":[23,245474,251591]},{"name":"12.5% C5G.ogg","ref":[23,251591,257703]},{"name":"12.5% C5C#.ogg","ref":[23,257703,263811]},{"name":"12.5% C5D.ogg","ref":[23,263811,269918]},{"name":"25% 39-1.ogg","ref":[23,269918,276023]},{"name":"12.5% C4D.ogg","ref":[23,276023,282127]},{"name":"12.5% C4A.ogg","ref":[23,282127,288225]},{"name":"triangle 97-8.ogg","ref":[23,288225,294323]},{"name":"25% 68-3.ogg","ref":[23,294323,300416]},{"name":"25% 68-1-1.ogg","ref":[23,300416,306509]},{"name":"12.5% C4E.ogg","ref":[23,306509,312597]},{"name":"12.5% C4C#.ogg","ref":[23,312597,318685]},{"name":"triangle 97-7.ogg","ref":[23,318685,324769]},{"name":"12.5% C6C#.ogg","ref":[23,324769,330848]},{"name":"25% 3-8.ogg","ref":[23,330848,336919]},{"name":"12.5% C4A#.ogg","ref":[23,336919,342990]},{"name":"12.5% C3A#.ogg","ref":[23,342990,349059]},{"name":"triangle 93-2.ogg","ref":[23,349059,355127]},{"name":"12.5% C3E.ogg","ref":[23,355127,361194]},{"name":"12.5% 16-1.ogg","ref":[23,361194,367258]},{"name":"12.5% 63-4.ogg","ref":[23,367258,373319]},{"name":"12.5% C4C.ogg","ref":[23,373319,379378]},{"name":"12.5% C3A.ogg","ref":[23,379378,385437]},{"name":"25% 3-7.ogg","ref":[23,385437,391489]},{"name":"25% 3-3.ogg","ref":[23,391489,397534]},{"name":"triangle 97-9.ogg","ref":[23,397534,403574]},{"name":"triangle 92-1.ogg","ref":[23,403574,409612]},{"name":"25% 68-4.ogg","ref":[23,409612,415647]},{"name":"triangle 97-5.ogg","ref":[23,415647,421681]},{"name":"25% 3-4.ogg","ref":[23,421681,427715]},{"name":"12.5% C3F#.ogg","ref":[23,427715,433736]},{"name":"triangle 94-1.ogg","ref":[23,433736,439754]},{"name":"triangle 31-5.ogg","ref":[23,439754,445751]},{"name":"12.5% 63-5.ogg","ref":[23,445751,451744]},{"name":"12.5% 65-2.ogg","ref":[23,451744,457737]},{"name":"25% 39-4.ogg","ref":[23,457737,463729]},{"name":"triangle 97-2.ogg","ref":[23,463729,469718]},{"name":"12.5% 70-2.ogg","ref":[23,469718,475707]},{"name":"25% 59-2-1.ogg","ref":[23,475707,481691]},{"name":"12.5% 69-1.ogg","ref":[23,481691,487671]},{"name":"12.5% 62-1.ogg","ref":[23,487671,493648]},{"name":"25% 40-4.ogg","ref":[23,493648,499621]},{"name":"25% 59-2-2.ogg","ref":[23,499621,505593]},{"name":"triangle 38-4.ogg","ref":[23,505593,511563]},{"name":"25% 39-8.ogg","ref":[23,511563,517531]},{"name":"12.5% 60-1.ogg","ref":[23,517531,523495]},{"name":"25% 62-2-2.ogg","ref":[23,523495,529456]},{"name":"25% 63-2-2.ogg","ref":[23,529456,535415]},{"name":"triangle 97-1.ogg","ref":[23,535415,541372]},{"name":"25% 39-6.ogg","ref":[23,541372,547322]},{"name":"12.5% 15-1.ogg","ref":[23,547322,553267]},{"name":"triangle 97-4.ogg","ref":[23,553267,559208]},{"name":"25% 39-5.ogg","ref":[23,559208,565148]},{"name":"25% 39-3.ogg","ref":[23,565148,571088]},{"name":"25% 3-9.ogg","ref":[23,571088,577028]},{"name":"25% 63-2-1.ogg","ref":[23,577028,582967]},{"name":"25% 62-2-1.ogg","ref":[23,582967,588900]},{"name":"25% 40-3.ogg","ref":[23,588900,594832]},{"name":"triangle 97-3.ogg","ref":[23,594832,600762]},{"name":"25% 40-8.ogg","ref":[23,600762,606690]},{"name":"25% 60-2-2.ogg","ref":[23,606690,612618]},{"name":"25% 40-1.ogg","ref":[23,612618,618545]},{"name":"25% 40-2.ogg","ref":[23,618545,624471]},{"name":"25% 71-1.ogg","ref":[23,624471,630397]},{"name":"triangle 94-2.ogg","ref":[23,630397,636322]},{"name":"25% 70-1.ogg","ref":[23,636322,642246]},{"name":"25% 4-2.ogg","ref":[23,642246,648169]},{"name":"25% 70-2.ogg","ref":[23,648169,654087]},{"name":"25% 39-9.ogg","ref":[23,654087,660003]},{"name":"25% 39-7.ogg","ref":[23,660003,665915]},{"name":"25% 39-10.ogg","ref":[23,665915,671825]},{"name":"25% 3-6.ogg","ref":[23,671825,677732]},{"name":"25% 3-5.ogg","ref":[23,677732,683633]},{"name":"25% 3-12.ogg","ref":[23,683633,689534]},{"name":"25% 70-3.ogg","ref":[23,689534,695433]},{"name":"25% 3-10.ogg","ref":[23,695433,701323]},{"name":"25% 3-11.ogg","ref":[23,701323,707213]},{"name":"25% 4-1.ogg","ref":[23,707213,713102]},{"name":"12.5% C6D.ogg","ref":[23,713102,718967]},{"name":"25% 60-2-1.ogg","ref":[23,718967,724825]},{"name":"triangle 33-bass.ogg","ref":[23,724825,730678]},{"name":"25% 53-bass2.ogg","ref":[23,730678,736512]},{"name":"triangle 97-6.ogg","ref":[23,736512,742323]},{"name":"triangle 94-3.ogg","ref":[23,742323,748124]},{"name":"triangle 93-3.ogg","ref":[23,748124,753919]},{"name":"12.5% 16-2.ogg","ref":[23,753919,759705]},{"name":"triangle 27-bass.ogg","ref":[23,759705,765488]},{"name":"25% 40-13.ogg","ref":[23,765488,771256]},{"name":"triangle 35-bass.ogg","ref":[23,771256,777020]},{"name":"triangle 28-bass.ogg","ref":[23,777020,782769]},{"name":"triangle 30-bass.ogg","ref":[23,782769,788518]},{"name":"triangle 26-bass.ogg","ref":[23,788518,794266]},{"name":"triangle 29-bass.ogg","ref":[23,794266,800010]},{"name":"triangle 5-1.ogg","ref":[23,800010,805739]},{"name":"triangle 36-bass.ogg","ref":[23,805739,811451]},{"name":"triangle 32-bass.ogg","ref":[23,811451,817163]},{"name":"25% 40-11.ogg","ref":[23,817163,822860]},{"name":"triangle 31-bass.ogg","ref":[23,822860,828551]},{"name":"triangle 25-bass.ogg","ref":[23,828551,834242]},{"name":"triangle 5-23.ogg","ref":[23,834242,839923]},{"name":"25% 40-9.ogg","ref":[23,839923,845600]},{"name":"25% 40-20.ogg","ref":[23,845600,851270]},{"name":"25% 40-10.ogg","ref":[23,851270,856935]},{"name":"25% 6-3.ogg","ref":[23,856935,862586]},{"name":"25% 40-12.ogg","ref":[23,862586,868234]},{"name":"25% 6-2.ogg","ref":[23,868234,873864]},{"name":"triangle 6-1.ogg","ref":[23,873864,879489]},{"name":"25% 40-14.ogg","ref":[23,879489,885105]},{"name":"triangle 17-4.ogg","ref":[23,885105,890717]},{"name":"triangle 6-2.ogg","ref":[23,890717,896317]},{"name":"triangle 5-3.ogg","ref":[23,896317,901915]},{"name":"triangle 30-1.ogg","ref":[23,901915,907512]},{"name":"triangle 5-24.ogg","ref":[23,907512,913097]},{"name":"triangle 5-22.ogg","ref":[23,913097,918682]},{"name":"25% 6-1.ogg","ref":[23,918682,924263]},{"name":"triangle 5-4.ogg","ref":[23,924263,929830]},{"name":"triangle 17-3.ogg","ref":[23,929830,935391]},{"name":"triangle 34-bass.ogg","ref":[23,935391,940947]},{"name":"25% 55-bass2.ogg","ref":[23,940947,946498]},{"name":"triangle 26-5.ogg","ref":[23,946498,952045]},{"name":"triangle 5-7.ogg","ref":[23,952045,957589]},{"name":"12.5% 16-5.ogg","ref":[23,957589,963120]},{"name":"triangle 5-16.ogg","ref":[23,963120,968650]},{"name":"triangle 5-9.ogg","ref":[23,968650,974180]},{"name":"triangle 31-1.ogg","ref":[23,974180,979709]},{"name":"triangle 17-5.ogg","ref":[23,979709,985235]},{"name":"triangle 17-2.ogg","ref":[23,985235,990759]},{"name":"triangle 6-6.ogg","ref":[23,990759,996282]},{"name":"triangle 5-8.ogg","ref":[23,996282,1001805]},{"name":"triangle 5-18.ogg","ref":[23,1001805,1007328]},{"name":"triangle 5-6.ogg","ref":[23,1007328,1012851]},{"name":"triangle 6-9.ogg","ref":[23,1012851,1018374]},{"name":"12.5% 16-8.ogg","ref":[23,1018374,1023896]},{"name":"12.5% 16-6.ogg","ref":[23,1023896,1029415]},{"name":"triangle 17-6.ogg","ref":[23,1029415,1034933]},{"name":"triangle 5-19.ogg","ref":[23,1034933,1040446]},{"name":"ｼﾝｾﾄﾞﾗﾑ ﾎﾟ5.ogg","ref":[23,1040446,1045959]},{"name":"triangle 6-4.ogg","ref":[23,1045959,1051472]},{"name":"12.5% 16-4.ogg","ref":[23,1051472,1056983]},{"name":"12.5% 16-7.ogg","ref":[23,1056983,1062490]},{"name":"triangle 5-11.ogg","ref":[23,1062490,1067995]},{"name":"triangle 6-11.ogg","ref":[23,1067995,1073500]},{"name":"12.5% 16-9.ogg","ref":[23,1073500,1079000]},{"name":"triangle 5-17.ogg","ref":[23,1079000,1084499]},{"name":"triangle 5-21.ogg","ref":[23,1084499,1089996]},{"name":"triangle 5-12.ogg","ref":[23,1089996,1095493]},{"name":"triangle 6-12.ogg","ref":[23,1095493,1100990]},{"name":"triangle 5-14.ogg","ref":[23,1100990,1106487]},{"name":"25% 12-1.ogg","ref":[23,1106487,1111981]},{"name":"triangle 5-13.ogg","ref":[23,1111981,1117475]},{"name":"12.5% 16-12.ogg","ref":[23,1117475,1122964]},{"name":"12.5% 16-3.ogg","ref":[23,1122964,1128453]},{"name":"triangle 5-2.ogg","ref":[23,1128453,1133941]},{"name":"25% 9-1.ogg","ref":[23,1133941,1139423]},{"name":"25% 54-bass2.ogg","ref":[23,1139423,1144904]},{"name":"12.5% 16-11.ogg","ref":[23,1144904,1150381]},{"name":"triangle 6-10.ogg","ref":[23,1150381,1155854]},{"name":"triangle 5-15.ogg","ref":[23,1155854,1161327]},{"name":"triangle 5-10.ogg","ref":[23,1161327,1166800]},{"name":"12.5% 16-13.ogg","ref":[23,1166800,1172272]},{"name":"triangle 33-1.ogg","ref":[23,1172272,1177738]},{"name":"triangle 34-2.ogg","ref":[23,1177738,1183203]},{"name":"triangle 28-1.ogg","ref":[23,1183203,1188666]},{"name":"12.5% 16-10.ogg","ref":[23,1188666,1194128]},{"name":"triangle 6-5.ogg","ref":[23,1194128,1199588]},{"name":"triangle 5-5.ogg","ref":[23,1199588,1205048]},{"name":"triangle 6-8.ogg","ref":[23,1205048,1210491]},{"name":"triangle 29-5.ogg","ref":[23,1210491,1215927]},{"name":"triangle 6-3.ogg","ref":[23,1215927,1221361]},{"name":"triangle 5-20.ogg","ref":[23,1221361,1226795]},{"name":"25% 13-1.ogg","ref":[23,1226795,1232216]},{"name":"triangle 32-2.ogg","ref":[23,1232216,1237621]},{"name":"25% 4-12.ogg","ref":[23,1237621,1243021]},{"name":"triangle 32-3.ogg","ref":[23,1243021,1248414]},{"name":"25% 4-11.ogg","ref":[23,1248414,1253807]},{"name":"ｼﾝｾﾄﾞﾗﾑ ﾎﾟ4.ogg","ref":[23,1253807,1259193]},{"name":"25% 4-9.ogg","ref":[23,1259193,1264573]},{"name":"25% 4-14.ogg","ref":[23,1264573,1269935]},{"name":"25% 4-15.ogg","ref":[23,1269935,1275289]},{"name":"25% 4-13.ogg","ref":[23,1275289,1280639]},{"name":"triangle 6-7.ogg","ref":[23,1280639,1285987]},{"name":"25% 4-8.ogg","ref":[23,1285987,1291334]},{"name":"triangle 29-2.ogg","ref":[23,1291334,1296677]},{"name":"25% 4-16.ogg","ref":[23,1296677,1302020]},{"name":"triangle 27-1.ogg","ref":[23,1302020,1307349]},{"name":"ｼﾝｾﾄﾞﾗﾑ ﾎﾟ2.ogg","ref":[23,1307349,1312661]},{"name":"triangle 95-2.ogg","ref":[23,1312661,1317961]},{"name":"ｼﾝｾﾄﾞﾗﾑ ﾎﾟ3.ogg","ref":[23,1317961,1323235]},{"name":"noise 100%.ogg","ref":[23,1323235,1328506]},{"name":"triangle 35-5.ogg","ref":[23,1328506,1333775]},{"name":"triangle 35-6.ogg","ref":[23,1333775,1339026]},{"name":"triangle 95-1.ogg","ref":[23,1339026,1344274]},{"name":"triangle 26-4.ogg","ref":[23,1344274,1349501]},{"name":"noise 75%.ogg","ref":[23,1349501,1354700]},{"name":"noise 65%.ogg","ref":[23,1354700,1359869]},{"name":"triangle 17-1.ogg","ref":[23,1359869,1365036]},{"name":"noise 50%.ogg","ref":[23,1365036,1370201]},{"name":"ｼﾝｾﾄﾞﾗﾑ ﾎﾟ1.ogg","ref":[23,1370201,1375322]},{"name":"ｼﾝｾﾄﾞﾗﾑ ﾎﾟ6.ogg","ref":[23,1375322,1380441]}],"refs":[{"path":"mp3.1.fa816e85.bemuse","hash":"fa816e8511321772d9ab87bce7ae13ff"},{"path":"mp3.2.5a6dec12.bemuse","hash":"5a6dec123253bea8da0fb6b4c419ad3f"},{"path":"mp3.3.5adf30cf.bemuse","hash":"5adf30cf5d86a3f36a250f6847cff1ae"},{"path":"mp3.4.a8d4d4ab.bemuse","hash":"a8d4d4ab2ae8c5124518187bf30c4bd1"},{"path":"mp3.5.207f3814.bemuse","hash":"207f38141d9719d2c042f1a98d96c562"},{"path":"mp3.6.5c76c61e.bemuse","hash":"5c76c61e2275ddbe72e21d5b33f50b99"},{"path":"mp3.7.253e2ec1.bemuse","hash":"253e2ec13b64dfc8fed5f6059ba4404a"},{"path":"mp3.8.2118551d.bemuse","hash":"2118551da1be16ab4873bc6630a50a0b"},{"path":"mp3.9.913f4395.bemuse","hash":"913f4395318bf91343cbf0690d79aaf9"},{"path":"mp3.10.912d8db0.bemuse","hash":"912d8db0720880fbfba6d29cc73ae676"},{"path":"mp3.11.7337a57f.bemuse","hash":"7337a57f32c728503d592cedcb4126e0"},{"path":"mp3.12.1d530245.bemuse","hash":"1d530245ba96afb10feeac4461b8bcd3"},{"path":"mp3.13.feb4b7d2.bemuse","hash":"feb4b7d2d8dcfe4196336eecd7ade505"},{"path":"bgv.1.9ae7d8a8.bemuse","hash":"9ae7d8a8cf4ddf34c3fce365d4cb41b3"},{"path":"ogg.1.9cee45a4.bemuse","hash":"9cee45a4f22134e037af8b4c02b2b2b0"},{"path":"ogg.2.fd5f13c1.bemuse","hash":"fd5f13c1564b0bf477a1523220a9b758"},{"path":"ogg.3.f0d733af.bemuse","hash":"f0d733afbc759d359ef854642e5137dc"},{"path":"ogg.4.0e53a7d2.bemuse","hash":"0e53a7d2325f3a994aed9e5e7ee1f6bf"},{"path":"ogg.5.86ec3531.bemuse","hash":"86ec3531efa80c662f58f395d801d44b"},{"path":"ogg.6.42069328.bemuse","hash":"420693284ab1b49cf21d17c20608b792"},{"path":"ogg.7.57bcf1e2.bemuse","hash":"57bcf1e2fbab177f247f965579831d34"},{"path":"ogg.8.592acccf.bemuse","hash":"592acccf851228b815dbb54ed6131e34"},{"path":"ogg.9.d1699395.bemuse","hash":"d16993957428e45d0a08c2ea97f1f524"},{"path":"ogg.10.fc56f255.bemuse","hash":"fc56f255080dbf701a492d6050df3a0f"}]}